Workbook

Sheet Consolidation_Summary
A1: Consolidated Version | B1: v8 lean / JD-fit
A2: Purpose | B2: Remove duplicate sheets and simplify Streamlit dashboard tabs while preserving content in core sheets.
A4: Removed Sheet | B4: Merged Into
A5: Meeting_Brief | B5: Meeting_Intelligence
A6: Regional_Report_Pack | B6: Executive_Brief
A7: Monthly_RO_Report_Generator | B7: Executive_Brief
A8: Relationship_Intelligence | B8: Regulator_CRM
A9: Risk_Radar | B9: Policy_Monitoring
A10: Regulatory_News_Feed | B10: Policy_Monitoring
A11: Interview_Story_Mode | B11: Interview_Demo_Mode
A12: Demo_Script_Mode | B12: Interview_Demo_Mode
A13: Version_Change_Log | B13: Removed
A14: Excel_Streamlit_Integration | B14: Removed from dashboard / concept retained in user guide

Sheet Executive_Dashboard
A1: Manulife Vietnam Regulatory & Public Affairs Command Center v4.0 (v3 fully inherited + v4 modules added)
A3: KPI | B3: Value | C3: Interpretation | D3: Formula / Source
A4: Reports due in 7 days | B4: =COUNTIF(Regulatory_Calendar!H2:H31,"Due Soon") | C4: Deadline pressure | D4: Regulatory_Calendar
A5: Overdue reports | B5: =COUNTIF(Regulatory_Calendar!H2:H31,"Overdue") | C5: Needs escalation | D5: Regulatory_Calendar
A6: Pending submissions | B6: =COUNTIFS(Submission_Tracker!I2:I61,"<>Submitted",Submission_Tracker!I2:I61,"<>Approved") | C6: Open workload | D6: Submission_Tracker
A7: Pending approvals | B7: =COUNTIFS(Approval_Pipeline!F2:F26,"<>Approved",Approval_Pipeline!F2:F26,"<>Rejected/Withdrawn") | C7: Regulatory pipeline | D7: Approval_Pipeline
A8: High policy risk items | B8: =COUNTIF(Policy_Monitoring!I2:I11,">=10") | C8: Early warning | D8: Policy_Monitoring
A9: Average relationship strength | B9: =ROUND(AVERAGE(Relationship_Intelligence!D2:D7),2) | C9: Regulator trust base | D9: Relationship_Intelligence
A10: Open follow-ups | B10: =COUNTIF(Regulator_Interactions!K2:K49,"Open") | C10: Action discipline | D10: Regulator_Interactions
A11: Translation overdue | B11: =COUNTIF(Translation_Tracker!G2:G21,"Overdue") | C11: Operational support | D11: Translation_Tracker
A13: Recommended Weekly Operating Rhythm
A14: Day | B14: Action | C14: Output | D14: Owner
A15: Monday | B15: Review deadline dashboard and overdue items | C15: Escalation list | D15: Public Affairs
A16: Tuesday | B16: Policy monitoring and regulator news scan | C16: Policy radar memo | D16: Public Affairs
A17: Wednesday | B17: Check submission quality and internal follow-up | C17: Submission status update | D17: Legal/Compliance/Business
A18: Thursday | B18: Prepare meeting briefs and regulator interaction notes | C18: Briefing pack | D18: Public Affairs
A19: Friday | B19: Regional Office reporting pack | C19: Weekly regulatory update | D19: Public Affairs
A21: How this model fits the JD: reporting documents, regulatory research, deadline reminders, official letter quality review, approvals support, regulator interactions, meeting logistics, translation tracker.
A23: v4 Add-on Modules | B23: Purpose | C23: Primary Output | D23: How Streamlit Uses It
A24: Regulator CRM | B24: Create institutional memory for MOF/ISA/IAV/MIC/SBV/VCA | C24: Regulator profile, open issues, relationship plan | D24: CRM tab + relationship drilldown
A25: Knowledge Base | B25: Store summaries of key laws/circulars and obligations | C25: Key obligations and affected departments | D25: Knowledge Base AI-lite tab
A26: Workflow Engine | B26: Standardize request-to-submission process | C26: Workflow stage, owner, SLA and bottlenecks | D26: Approval/Submission workflow tab
A27: Executive Brief Generator | B27: Generate 30-second daily/weekly regulatory brief | C27: CEO/EMT style brief | D27: Executive Brief tab
A28: Approval Time Analytics | B28: Analyze average regulator approval time | C28: Lead-time benchmarks and bottlenecks | D28: Approval Analytics tab
A29: Public Affairs Scorecard | B29: Translate PA operations into measurable KPIs | C29: On-time rate, relationship score, risk closure | D29: Scorecard tab
A30: Risk Radar | B30: Quantify regulatory probability x impact | C30: High-priority risk heatmap | D30: Risk Radar tab

Sheet Regulatory_Calendar
A1: Obligation ID | B1: Report / Obligation | C1: Regulator | D1: Frequency | E1: Owner Dept | F1: Due Date | G1: Days to Due | H1: Status | I1: Quality Check | J1: Escalation | K1: Notes
A2: CAL-001 | B2: Monthly solvency monitoring report | C2: ISA | D2: Monthly | E2: Product | F2: 46179 | G2: =F2-TODAY() | H2: Overdue | I2: In Progress | J2: Yes | K2: Sample data - replace with actual obligation
A3: CAL-002 | B3: Quarterly capital adequacy report | C3: MOF | D3: Quarterly | E3: Agency | F3: 46187 | G3: =F3-TODAY() | H3: Due Soon | I3: Not Started | J3: No | K3: Sample data - replace with actual obligation
A4: CAL-003 | B4: Annual audited financial statement filing | C4: MOF | D4: Annual | E4: Bancassurance | F4: 46184 | G4: =F4-TODAY() | H4: Due Soon | I4: Completed | J4: No | K4: Sample data - replace with actual obligation
A5: CAL-004 | B5: Product approval status update | C5: ISA | D5: Ad-hoc | E5: Operations | F5: 46179 | G5: =F5-TODAY() | H5: Submitted | I5: Completed | J5: No | K5: Sample data - replace with actual obligation
A6: CAL-005 | B6: Agency training approval report | C6: ISA | D6: Monthly | E6: CEO Office | F6: 46179 | G6: =F6-TODAY() | H6: Submitted | I6: Not Started | J6: No | K6: Sample data - replace with actual obligation
A7: CAL-006 | B7: Bancassurance compliance update | C7: SBV | D7: Quarterly | E7: Legal | F7: 46172 | G7: =F7-TODAY() | H7: Overdue | I7: Not Started | J7: Yes | K7: Sample data - replace with actual obligation
A8: CAL-007 | B8: Consumer complaint summary | C8: VCA | D8: Monthly | E8: Compliance | F8: 46219 | G8: =F8-TODAY() | H8: On Track | I8: Completed | J8: No | K8: Sample data - replace with actual obligation
A9: CAL-008 | B9: AML / CFT compliance certification | C9: MOF | D9: Annual | E9: Finance | F9: 46172 | G9: =F9-TODAY() | H9: Submitted | I9: Completed | J9: No | K9: Sample data - replace with actual obligation
A10: CAL-009 | B10: Data privacy compliance update | C10: MIC | D10: Quarterly | E10: Product | F10: 46219 | G10: =F10-TODAY() | H10: On Track | I10: In Progress | J10: No | K10: Sample data - replace with actual obligation
A11: CAL-010 | B11: Market conduct remediation update | C11: ISA | D11: Ad-hoc | E11: Agency | F11: 46187 | G11: =F11-TODAY() | H11: Due Soon | I11: In Progress | J11: No | K11: Sample data - replace with actual obligation
A12: CAL-011 | B12: Regional Office regulatory update | C12: Regional Office | D12: Monthly | E12: Bancassurance | F12: 46232 | G12: =F12-TODAY() | H12: On Track | I12: In Progress | J12: No | K12: Sample data - replace with actual obligation
A13: CAL-012 | B13: Ad-hoc ISA information request | C13: ISA | D13: Ad-hoc | E13: Operations | F13: 46172 | G13: =F13-TODAY() | H13: Submitted | I13: Not Started | J13: No | K13: Sample data - replace with actual obligation
... A31: CAL-030 | B31: Bancassurance compliance update | C31: SBV | D31: Quarterly | E31: Legal | F31: 46192 | G31: =F31-TODAY() | H31: On Track | I31: In Progress | J31: No | K31: Sample data - replace with actual obligation

Sheet Submission_Tracker
A1: Submission ID | B1: Document / Request | C1: Regulator | D1: Submission Type | E1: Owner Dept | F1: Received Date | G1: Submission Due Date | H1: Submitted Date | I1: Status | J1: Lead Time Days | K1: Checklist Complete | L1: Risk Level | M1: Next Action
A2: SUB-001 | B2: License/Transaction - item 1 | C2: MOF | D2: Agency Training | E2: Finance | F2: 46157 | G2: 46183 | I2: In Review | J2: =IF(H2="",TODAY()-F2,H2-F2) | K2: Partial | L2: Low | M2: Follow-up / quality review
A3: SUB-002 | B3: License/Transaction - item 2 | C3: SBV | D3: Report | E3: Bancassurance | F3: 46152 | G3: 46162 | H3: 46160 | I3: Submitted | J3: =IF(H3="",TODAY()-F3,H3-F3) | K3: Yes | L3: High | M3: Follow-up / quality review
A4: SUB-003 | B4: New Product Approval - item 3 | C4: MOF | D4: Report | E4: Bancassurance | F4: 46179 | G4: 46209 | I4: In Review | J4: =IF(H4="",TODAY()-F4,H4-F4) | K4: Yes | L4: Low | M4: Follow-up / quality review
A5: SUB-004 | B5: Report - item 4 | C5: IAV | D5: Report | E5: Product | F5: 46120 | G5: 46137 | H5: 46134 | I5: Approved | J5: =IF(H5="",TODAY()-F5,H5-F5) | K5: Partial | L5: Low | M5: Follow-up / quality review
A6: SUB-005 | B6: Agency Training - item 5 | C6: MIC | D6: New Product Approval | E6: Product | F6: 46115 | G6: 46128 | H6: 46125 | I6: Approved | J6: =IF(H6="",TODAY()-F6,H6-F6) | K6: Yes | L6: Low | M6: Follow-up / quality review
A7: SUB-006 | B7: Report - item 6 | C7: ISA | D7: Ad-hoc Response | E7: Operations | F7: 46120 | G7: 46127 | H7: 46127 | I7: Approved | J7: =IF(H7="",TODAY()-F7,H7-F7) | K7: Partial | L7: High | M7: Follow-up / quality review
A8: SUB-007 | B8: Agency Training - item 7 | C8: IAV | D8: Agency Training | E8: Legal | F8: 46134 | G8: 46151 | H8: 46148 | I8: Submitted | J8: =IF(H8="",TODAY()-F8,H8-F8) | K8: Partial | L8: Low | M8: Follow-up / quality review
A9: SUB-008 | B9: Ad-hoc Response - item 8 | C9: IAV | D9: Official Letter | E9: Agency | F9: 46169 | G9: 46195 | H9: 46193 | I9: Approved | J9: =IF(H9="",TODAY()-F9,H9-F9) | K9: No | L9: High | M9: Follow-up / quality review
A10: SUB-009 | B10: License/Transaction - item 9 | C10: IAV | D10: Agency Training | E10: Finance | F10: 46125 | G10: 46130 | I10: Overdue | J10: =IF(H10="",TODAY()-F10,H10-F10) | K10: Partial | L10: High | M10: Follow-up / quality review
A11: SUB-010 | B11: Report - item 10 | C11: IAV | D11: Ad-hoc Response | E11: Finance | F11: 46103 | G11: 46117 | H11: 46116 | I11: Approved | J11: =IF(H11="",TODAY()-F11,H11-F11) | K11: Partial | L11: Low | M11: Follow-up / quality review
A12: SUB-011 | B12: Official Letter - item 11 | C12: MOF | D12: New Product Approval | E12: Agency | F12: 46183 | G12: 46207 | I12: In Review | J12: =IF(H12="",TODAY()-F12,H12-F12) | K12: Yes | L12: High | M12: Follow-up / quality review
A13: SUB-012 | B13: Official Letter - item 12 | C13: MIC | D13: Ad-hoc Response | E13: Compliance | F13: 46153 | G13: 46176 | I13: Overdue | J13: =IF(H13="",TODAY()-F13,H13-F13) | K13: Partial | L13: High | M13: Follow-up / quality review
A14: SUB-013 | B14: New Product Approval - item 13 | C14: SBV | D14: Ad-hoc Response | E14: Operations | F14: 46167 | G14: 46193 | H14: 46192 | I14: Submitted | J14: =IF(H14="",TODAY()-F14,H14-F14) | K14: Yes | L14: Low | M14: Follow-up / quality review
A15: SUB-014 | B15: Capital Injection - item 14 | C15: IAV | D15: Capital Injection | E15: CEO Office | F15: 46087 | G15: 46115 | H15: 46113 | I15: Approved | J15: =IF(H15="",TODAY()-F15,H15-F15) | K15: Yes | L15: High | M15: Follow-up / quality review
A16: SUB-015 | B16: Agency Training - item 15 | C16: SBV | D16: Report | E16: Product | F16: 46155 | G16: 46162 | I16: In Review | J16: =IF(H16="",TODAY()-F16,H16-F16) | K16: Yes | L16: High | M16: Follow-up / quality review
A17: SUB-016 | B17: Official Letter - item 16 | C17: MOF | D17: Ad-hoc Response | E17: Bancassurance | F17: 46093 | G17: 46118 | I17: Drafting | J17: =IF(H17="",TODAY()-F17,H17-F17) | K17: Yes | L17: Low | M17: Follow-up / quality review
A18: SUB-017 | B18: Agency Training - item 17 | C18: ISA | D18: License/Transaction | E18: CEO Office | F18: 46153 | G18: 46166 | H18: 46165 | I18: Approved | J18: =IF(H18="",TODAY()-F18,H18-F18) | K18: Yes | L18: Medium | M18: Follow-up / quality review
A19: SUB-018 | B19: License/Transaction - item 18 | C19: MIC | D19: New Product Approval | E19: Operations | F19: 46131 | G19: 46142 | I19: Drafting | J19: =IF(H19="",TODAY()-F19,H19-F19) | K19: No | L19: Medium | M19: Follow-up / quality review
A20: SUB-019 | B20: Official Letter - item 19 | C20: MIC | D20: License/Transaction | E20: Bancassurance | F20: 46090 | G20: 46096 | H20: 46096 | I20: Approved | J20: =IF(H20="",TODAY()-F20,H20-F20) | K20: Yes | L20: High | M20: Follow-up / quality review
A21: SUB-020 | B21: Capital Injection - item 20 | C21: ISA | D21: New Product Approval | E21: CEO Office | F21: 46159 | G21: 46170 | H21: 46169 | I21: Submitted | J21: =IF(H21="",TODAY()-F21,H21-F21) | K21: Yes | L21: High | M21: Follow-up / quality review
A22: SUB-021 | B22: Official Letter - item 21 | C22: SBV | D22: Ad-hoc Response | E22: Legal | F22: 46127 | G22: 46157 | H22: 46157 | I22: Approved | J22: =IF(H22="",TODAY()-F22,H22-F22) | K22: Yes | L22: High | M22: Follow-up / quality review
A23: SUB-022 | B23: Ad-hoc Response - item 22 | C23: MIC | D23: Official Letter | E23: Finance | F23: 46162 | G23: 46180 | H23: 46179 | I23: Submitted | J23: =IF(H23="",TODAY()-F23,H23-F23) | K23: No | L23: High | M23: Follow-up / quality review
A24: SUB-023 | B24: Ad-hoc Response - item 23 | C24: MIC | D24: New Product Approval | E24: Operations | F24: 46134 | G24: 46147 | I24: Overdue | J24: =IF(H24="",TODAY()-F24,H24-F24) | K24: Partial | L24: Low | M24: Follow-up / quality review
A25: SUB-024 | B25: Report - item 24 | C25: IAV | D25: Report | E25: Legal | F25: 46112 | G25: 46138 | H25: 46137 | I25: Approved | J25: =IF(H25="",TODAY()-F25,H25-F25) | K25: Partial | L25: Low | M25: Follow-up / quality review
A26: SUB-025 | B26: Official Letter - item 25 | C26: SBV | D26: Capital Injection | E26: Finance | F26: 46114 | G26: 46120 | H26: 46120 | I26: Approved | J26: =IF(H26="",TODAY()-F26,H26-F26) | K26: Yes | L26: Low | M26: Follow-up / quality review
A27: SUB-026 | B27: Official Letter - item 26 | C27: ISA | D27: Capital Injection | E27: Compliance | F27: 46173 | G27: 46183 | I27: Drafting | J27: =IF(H27="",TODAY()-F27,H27-F27) | K27: Partial | L27: High | M27: Follow-up / quality review
A28: SUB-027 | B28: Official Letter - item 27 | C28: MIC | D28: License/Transaction | E28: Bancassurance | F28: 46109 | G28: 46133 | I28: Drafting | J28: =IF(H28="",TODAY()-F28,H28-F28) | K28: No | L28: High | M28: Follow-up / quality review
A29: SUB-028 | B29: New Product Approval - item 28 | C29: MIC | D29: Report | E29: Agency | F29: 46098 | G29: 46125 | I29: In Review | J29: =IF(H29="",TODAY()-F29,H29-F29) | K29: No | L29: Medium | M29: Follow-up / quality review
A30: SUB-029 | B30: Agency Training - item 29 | C30: SBV | D30: Official Letter | E30: Compliance | F30: 46087 | G30: 46094 | I30: Drafting | J30: =IF(H30="",TODAY()-F30,H30-F30) | K30: Partial | L30: High | M30: Follow-up / quality review
A31: SUB-030 | B31: New Product Approval - item 30 | C31: MOF | D31: Report | E31: Bancassurance | F31: 46119 | G31: 46132 | I31: Waiting Internal Input | J31: =IF(H31="",TODAY()-F31,H31-F31) | K31: No | L31: High | M31: Follow-up / quality review
A32: SUB-031 | B32: License/Transaction - item 31 | C32: SBV | D32: New Product Approval | E32: Compliance | F32: 46127 | G32: 46149 | H32: 46149 | I32: Approved | J32: =IF(H32="",TODAY()-F32,H32-F32) | K32: Yes | L32: Medium | M32: Follow-up / quality review
A33: SUB-032 | B33: New Product Approval - item 32 | C33: IAV | D33: Agency Training | E33: Product | F33: 46169 | G33: 46177 | H33: 46176 | I33: Approved | J33: =IF(H33="",TODAY()-F33,H33-F33) | K33: Partial | L33: Medium | M33: Follow-up / quality review
A34: SUB-033 | B34: Agency Training - item 33 | C34: MIC | D34: New Product Approval | E34: Legal | F34: 46157 | G34: 46183 | H34: 46181 | I34: Submitted | J34: =IF(H34="",TODAY()-F34,H34-F34) | K34: Yes | L34: Low | M34: Follow-up / quality review
A35: SUB-034 | B35: New Product Approval - item 34 | C35: ISA | D35: License/Transaction | E35: Agency | F35: 46129 | G35: 46142 | I35: Drafting | J35: =IF(H35="",TODAY()-F35,H35-F35) | K35: Yes | L35: Low | M35: Follow-up / quality review
A36: SUB-035 | B36: Official Letter - item 35 | C36: MOF | D36: License/Transaction | E36: Finance | F36: 46127 | G36: 46149 | H36: 46149 | I36: Approved | J36: =IF(H36="",TODAY()-F36,H36-F36) | K36: Partial | L36: High | M36: Follow-up / quality review
A37: SUB-036 | B37: Report - item 36 | C37: MOF | D37: New Product Approval | E37: Bancassurance | F37: 46136 | G37: 46159 | H37: 46156 | I37: Submitted | J37: =IF(H37="",TODAY()-F37,H37-F37) | K37: Yes | L37: Medium | M37: Follow-up / quality review
A38: SUB-037 | B38: Official Letter - item 37 | C38: IAV | D38: Ad-hoc Response | E38: Operations | F38: 46157 | G38: 46183 | I38: In Review | J38: =IF(H38="",TODAY()-F38,H38-F38) | K38: Partial | L38: Low | M38: Follow-up / quality review
A39: SUB-038 | B39: Capital Injection - item 38 | C39: MOF | D39: Report | E39: Bancassurance | F39: 46164 | G39: 46176 | H39: 46175 | I39: Approved | J39: =IF(H39="",TODAY()-F39,H39-F39) | K39: No | L39: Low | M39: Follow-up / quality review
A40: SUB-039 | B40: Report - item 39 | C40: MOF | D40: Capital Injection | E40: Legal | F40: 46089 | G40: 46119 | I40: In Review | J40: =IF(H40="",TODAY()-F40,H40-F40) | K40: No | L40: High | M40: Follow-up / quality review
A41: SUB-040 | B41: Ad-hoc Response - item 40 | C41: ISA | D41: Report | E41: Legal | F41: 46158 | G41: 46177 | I41: In Review | J41: =IF(H41="",TODAY()-F41,H41-F41) | K41: Partial | L41: High | M41: Follow-up / quality review
A42: SUB-041 | B42: Official Letter - item 41 | C42: IAV | D42: New Product Approval | E42: Operations | F42: 46132 | G42: 46147 | I42: In Review | J42: =IF(H42="",TODAY()-F42,H42-F42) | K42: Partial | L42: Low | M42: Follow-up / quality review
A43: SUB-042 | B43: New Product Approval - item 42 | C43: ISA | D43: Agency Training | E43: Agency | F43: 46141 | G43: 46146 | I43: Drafting | J43: =IF(H43="",TODAY()-F43,H43-F43) | K43: Yes | L43: High | M43: Follow-up / quality review
A44: SUB-043 | B44: Ad-hoc Response - item 43 | C44: IAV | D44: Capital Injection | E44: Compliance | F44: 46107 | G44: 46125 | I44: In Review | J44: =IF(H44="",TODAY()-F44,H44-F44) | K44: No | L44: Low | M44: Follow-up / quality review
A45: SUB-044 | B45: Capital Injection - item 44 | C45: MOF | D45: Agency Training | E45: Product | F45: 46159 | G45: 46172 | I45: Drafting | J45: =IF(H45="",TODAY()-F45,H45-F45) | K45: No | L45: Medium | M45: Follow-up / quality review
A46: SUB-045 | B46: Agency Training - item 45 | C46: IAV | D46: License/Transaction | E46: Compliance | F46: 46175 | G46: 46201 | I46: Overdue | J46: =IF(H46="",TODAY()-F46,H46-F46) | K46: Partial | L46: Medium | M46: Follow-up / quality review
A47: SUB-046 | B47: Capital Injection - item 46 | C47: IAV | D47: Agency Training | E47: Finance | F47: 46119 | G47: 46133 | H47: 46131 | I47: Approved | J47: =IF(H47="",TODAY()-F47,H47-F47) | K47: Yes | L47: Medium | M47: Follow-up / quality review
A48: SUB-047 | B48: Agency Training - item 47 | C48: SBV | D48: New Product Approval | E48: Operations | F48: 46098 | G48: 46115 | H48: 46114 | I48: Approved | J48: =IF(H48="",TODAY()-F48,H48-F48) | K48: Partial | L48: High | M48: Follow-up / quality review
A49: SUB-048 | B49: Ad-hoc Response - item 48 | C49: SBV | D49: Agency Training | E49: Bancassurance | F49: 46145 | G49: 46159 | I49: Waiting Internal Input | J49: =IF(H49="",TODAY()-F49,H49-F49) | K49: No | L49: Medium | M49: Follow-up / quality review
A50: SUB-049 | B50: Capital Injection - item 49 | C50: ISA | D50: License/Transaction | E50: Compliance | F50: 46127 | G50: 46153 | I50: Waiting Internal Input | J50: =IF(H50="",TODAY()-F50,H50-F50) | K50: No | L50: Low | M50: Follow-up / quality review
A51: SUB-050 | B51: Ad-hoc Response - item 50 | C51: ISA | D51: License/Transaction | E51: Agency | F51: 46099 | G51: 46124 | H51: 46124 | I51: Submitted | J51: =IF(H51="",TODAY()-F51,H51-F51) | K51: Yes | L51: High | M51: Follow-up / quality review
A52: SUB-051 | B52: Capital Injection - item 51 | C52: SBV | D52: Ad-hoc Response | E52: Compliance | F52: 46165 | G52: 46170 | I52: Drafting | J52: =IF(H52="",TODAY()-F52,H52-F52) | K52: No | L52: Medium | M52: Follow-up / quality review
A53: SUB-052 | B53: License/Transaction - item 52 | C53: MIC | D53: Capital Injection | E53: Operations | F53: 46103 | G53: 46126 | I53: Waiting Internal Input | J53: =IF(H53="",TODAY()-F53,H53-F53) | K53: Yes | L53: High | M53: Follow-up / quality review
A54: SUB-053 | B54: Ad-hoc Response - item 53 | C54: MOF | D54: Ad-hoc Response | E54: Operations | F54: 46100 | G54: 46127 | I54: Drafting | J54: =IF(H54="",TODAY()-F54,H54-F54) | K54: Yes | L54: High | M54: Follow-up / quality review
A55: SUB-054 | B55: Ad-hoc Response - item 54 | C55: MOF | D55: Capital Injection | E55: Finance | F55: 46094 | G55: 46115 | H55: 46114 | I55: Submitted | J55: =IF(H55="",TODAY()-F55,H55-F55) | K55: No | L55: Low | M55: Follow-up / quality review
A56: SUB-055 | B56: Agency Training - item 55 | C56: SBV | D56: Capital Injection | E56: CEO Office | F56: 46116 | G56: 46138 | H56: 46135 | I56: Submitted | J56: =IF(H56="",TODAY()-F56,H56-F56) | K56: Yes | L56: Low | M56: Follow-up / quality review
A57: SUB-056 | B57: Report - item 56 | C57: IAV | D57: Ad-hoc Response | E57: CEO Office | F57: 46123 | G57: 46142 | I57: In Review | J57: =IF(H57="",TODAY()-F57,H57-F57) | K57: Partial | L57: High | M57: Follow-up / quality review
A58: SUB-057 | B58: New Product Approval - item 57 | C58: ISA | D58: New Product Approval | E58: Bancassurance | F58: 46148 | G58: 46167 | I58: Drafting | J58: =IF(H58="",TODAY()-F58,H58-F58) | K58: No | L58: Low | M58: Follow-up / quality review
A59: SUB-058 | B59: Capital Injection - item 58 | C59: ISA | D59: License/Transaction | E59: Product | F59: 46173 | G59: 46182 | I59: Waiting Internal Input | J59: =IF(H59="",TODAY()-F59,H59-F59) | K59: Yes | L59: Medium | M59: Follow-up / quality review
A60: SUB-059 | B60: Official Letter - item 59 | C60: ISA | D60: Ad-hoc Response | E60: Operations | F60: 46131 | G60: 46146 | H60: 46143 | I60: Submitted | J60: =IF(H60="",TODAY()-F60,H60-F60) | K60: No | L60: Low | M60: Follow-up / quality review
A61: SUB-060 | B61: Capital Injection - item 60 | C61: MOF | D61: New Product Approval | E61: Agency | F61: 46094 | G61: 46099 | H61: 46096 | I61: Approved | J61: =IF(H61="",TODAY()-F61,H61-F61) | K61: No | L61: Medium | M61: Follow-up / quality review

Sheet Approval_Pipeline
A1: Approval ID | B1: Approval Item | C1: Category | D1: Regulator | E1: Business Owner | F1: Current Stage | G1: Request Date | H1: Target Approval Date | I1: Days in Pipeline | J1: Probability of Approval (%) | K1: Business Impact | L1: Blocker | M1: Next Action
A2: APR-001 | B2: Health Rider Update 1 | C2: License | D2: MOF | E2: Agency | F2: Approved | G2: 46111 | H2: 46200 | I2: =TODAY()-G2 | J2: 72 | K2: Medium | L2: None | M2: Prepare response / follow up
A3: APR-002 | B3: Agency Training Program 2 | C3: Distribution | D3: MOF | E3: Bancassurance | F3: Regulator Q&A | G3: 46130 | H3: 46193 | I3: =TODAY()-G3 | J3: 53 | K3: Low | L3: Internal sign-off | M3: Prepare response / follow up
A4: APR-003 | B4: License Amendment 3 | C4: Product | D4: MOF | E4: Bancassurance | F4: Regulator Q&A | G4: 46176 | H4: 46246 | I4: =TODAY()-G4 | J4: 53 | K4: Medium | L4: Awaiting legal memo | M4: Prepare response / follow up
A5: APR-004 | B5: Health Rider Update 4 | C5: License | D5: ISA | E5: Agency | F5: Submitted to Regulator | G5: 46173 | H5: 46226 | I5: =TODAY()-G5 | J5: 93 | K5: Medium | L5: Missing attachment | M5: Prepare response / follow up
A6: APR-005 | B6: New UL Product 5 | C6: License | D6: MOF | E6: CEO Office | F6: Compliance Review | G6: 46083 | H6: 46156 | I6: =TODAY()-G6 | J6: 48 | K6: Medium | L6: Awaiting legal memo | M6: Prepare response / follow up
A7: APR-006 | B7: License Amendment 6 | C7: Product | D7: MOF | E7: Finance | F7: Approved | G7: 46096 | H7: 46124 | I7: =TODAY()-G7 | J7: 57 | K7: High | L7: Internal sign-off | M7: Prepare response / follow up
A8: APR-007 | B8: License Amendment 7 | C8: Product | D8: MOF | E8: Bancassurance | F8: Legal Review | G8: 46160 | H8: 46210 | I8: =TODAY()-G8 | J8: 89 | K8: Medium | L8: Missing attachment | M8: Prepare response / follow up
A9: APR-008 | B9: Health Rider Update 8 | C9: Agency | D9: MOF | E9: CEO Office | F9: Approved | G9: 46158 | H9: 46192 | I9: =TODAY()-G9 | J9: 46 | K9: Medium | L9: Internal sign-off | M9: Prepare response / follow up
A10: APR-009 | B10: License Amendment 9 | C10: Capital | D10: MOF | E10: CEO Office | F10: Submitted to Regulator | G10: 46093 | H10: 46161 | I10: =TODAY()-G10 | J10: 89 | K10: Low | L10: Awaiting legal memo | M10: Prepare response / follow up
A11: APR-010 | B11: Bancassurance Campaign 10 | C11: Product | D11: MOF | E11: Agency | F11: Approved | G11: 46166 | H11: 46224 | I11: =TODAY()-G11 | J11: 79 | K11: Medium | L11: Missing attachment | M11: Prepare response / follow up
A12: APR-011 | B12: New UL Product 11 | C12: License | D12: ISA | E12: Product | F12: Regulator Q&A | G12: 46171 | H12: 46255 | I12: =TODAY()-G12 | J12: 72 | K12: Medium | L12: Regulator Q&A | M12: Prepare response / follow up
A13: APR-012 | B13: License Amendment 12 | C13: Transaction | D13: ISA | E13: CEO Office | F13: Submitted to Regulator | G13: 46089 | H13: 46128 | I13: =TODAY()-G13 | J13: 79 | K13: Medium | L13: Regulator Q&A | M13: Prepare response / follow up
... A26: APR-025 | B26: Agency Training Program 25 | C26: License | D26: ISA | E26: Agency | F26: Approved | G26: 46103 | H26: 46151 | I26: =TODAY()-G26 | J26: 82 | K26: Medium | L26: Missing attachment | M26: Prepare response / follow up

Sheet Regulator_Interactions
A1: Interaction ID | B1: Date | C1: Regulator | D1: Person / Unit | E1: Topic | F1: Interaction Type | G1: Tone | H1: Key Message | I1: Follow-up Owner | J1: Follow-up Due | K1: Status
A2: INT-001 | B2: 45601 | C2: MIC | D2: Policy Dept | E2: Capital requirement | F2: Call | G2: Neutral | H2: Provide transparent update and confirm next steps | I2: Agency | J2: 45606 | K2: Open
A3: INT-002 | B3: 45938 | C3: ISA | D3: Association Secretariat | E3: Capital requirement | F3: Call | G3: Positive | H3: Provide transparent update and confirm next steps | I3: Operations | J3: 45955 | K3: In Progress
A4: INT-003 | B4: 45575 | C4: SBV | D4: Insurance Supervision Team | E4: Product approval | F4: Call | G4: Cautious | H4: Provide transparent update and confirm next steps | I4: Agency | J4: 45592 | K4: Open
A5: INT-004 | B5: 45480 | C5: ISA | D5: Insurance Supervision Team | E5: Consumer complaints | F5: Submission counter | G5: Positive | H5: Provide transparent update and confirm next steps | I5: Product | J5: 45487 | K5: Closed
A6: INT-005 | B6: 46038 | C6: MOF | D6: Policy Dept | E6: Market conduct | F6: Email | G6: Cautious | H6: Provide transparent update and confirm next steps | I6: CEO Office | J6: 46044 | K6: Closed
A7: INT-006 | B7: 45478 | C7: IAV | D7: Legal Unit | E7: Data privacy | F7: Workshop | G7: Concerned | H7: Provide transparent update and confirm next steps | I7: CEO Office | J7: 45483 | K7: In Progress
A8: INT-007 | B8: 46143 | C8: SBV | D8: Insurance Supervision Team | E8: Data privacy | F8: Meeting | G8: Positive | H8: Provide transparent update and confirm next steps | I8: Product | J8: 46146 | K8: In Progress
A9: INT-008 | B9: 45908 | C9: MIC | D9: Policy Dept | E9: Market conduct | F9: Submission counter | G9: Concerned | H9: Provide transparent update and confirm next steps | I9: Agency | J9: 45916 | K9: In Progress
A10: INT-009 | B10: 45737 | C10: VCA | D10: Legal Unit | E10: Capital requirement | F10: Submission counter | G10: Cautious | H10: Provide transparent update and confirm next steps | I10: Operations | J10: 45750 | K10: Closed
A11: INT-010 | B11: 45497 | C11: MOF | D11: Administrative Office | E11: Bancassurance | F11: Submission counter | G11: Concerned | H11: Provide transparent update and confirm next steps | I11: Agency | J11: 45512 | K11: In Progress
A12: INT-011 | B12: 46146 | C12: SBV | D12: Policy Dept | E12: Bancassurance | F12: Email | G12: Cautious | H12: Provide transparent update and confirm next steps | I12: Compliance | J12: 46161 | K12: In Progress
A13: INT-012 | B13: 46182 | C13: VCA | D13: Association Secretariat | E13: ESG reporting | F13: Submission counter | G13: Positive | H13: Provide transparent update and confirm next steps | I13: Product | J13: 46201 | K13: Closed
... A49: INT-048 | B49: 46157 | C49: ISA | D49: Policy Dept | E49: Bancassurance | F49: Call | G49: Cautious | H49: Provide transparent update and confirm next steps | I49: Legal | J49: 46165 | K49: Closed

Sheet Policy_Monitoring
A1: Policy ID | B1: Policy / Regulation | C1: Agency | D1: Policy Stage | E1: Expected Timeline | F1: Probability (%) | G1: Business Impact (1-5) | H1: Reputation Impact (1-5) | I1: Risk Score | J1: Opportunity | K1: Recommended Action | L1: Owner
A2: POL-001 | B2: Insurance Law amendment | C2: MOF | D2: Draft discussion | E2: 0-3 months | F2: 38 | G2: 3 | H2: 4 | I2: =ROUND(F2*G2*H2/100,2) | J2: High | K2: Monitor, prepare internal memo and engage via association | L2: Legal
A3: POL-002 | B3: Circular on product approval process | C3: ISA | D3: Consultation | E3: 0-3 months | F3: 65 | G3: 5 | H3: 3 | I3: =ROUND(F3*G3*H3/100,2) | J3: Medium | K3: Monitor, prepare internal memo and engage via association | L3: Compliance
A4: POL-003 | B4: Bancassurance conduct guideline | C4: SBV / MOF | D4: Drafting | E4: 6-12 months | F4: 74 | G4: 2 | H4: 5 | I4: =ROUND(F4*G4*H4/100,2) | J4: Medium | K4: Monitor, prepare internal memo and engage via association | L4: Legal
A5: POL-004 | B5: Personal data protection implementation | C5: MIC | D5: Implementation | E5: 12+ months | F5: 38 | G5: 5 | H5: 4 | I5: =ROUND(F5*G5*H5/100,2) | J5: High | K5: Monitor, prepare internal memo and engage via association | L5: Legal
A6: POL-005 | B6: Consumer protection reporting requirement | C6: VCA | D6: Effective soon | E6: 0-3 months | F6: 66 | G6: 5 | H6: 1 | I6: =ROUND(F6*G6*H6/100,2) | J6: Medium | K6: Monitor, prepare internal memo and engage via association | L6: Compliance
A7: POL-006 | B7: Mandatory ESG disclosure for insurers | C7: MOF | D7: Early consultation | E7: 6-12 months | F7: 39 | G7: 3 | H7: 3 | I7: =ROUND(F7*G7*H7/100,2) | J7: Medium | K7: Monitor, prepare internal memo and engage via association | L7: Public Affairs
A8: POL-007 | B8: Capital adequacy and solvency update | C8: ISA | D8: Consultation | E8: 0-3 months | F8: 64 | G8: 5 | H8: 1 | I8: =ROUND(F8*G8*H8/100,2) | J8: High | K8: Monitor, prepare internal memo and engage via association | L8: Compliance
A9: POL-008 | B9: Agency training standard revision | C9: ISA | D9: Drafting | E9: 12+ months | F9: 62 | G9: 5 | H9: 2 | I9: =ROUND(F9*G9*H9/100,2) | J9: Medium | K9: Monitor, prepare internal memo and engage via association | L9: Risk
A10: POL-009 | B10: Digital insurance distribution rules | C10: MIC / MOF | D10: Policy design | E10: 6-12 months | F10: 60 | G10: 5 | H10: 1 | I10: =ROUND(F10*G10*H10/100,2) | J10: Medium | K10: Monitor, prepare internal memo and engage via association | L10: Public Affairs
A11: POL-010 | B11: Complaint handling transparency requirement | C11: VCA / ISA | D11: Drafting | E11: 3-6 months | F11: 77 | G11: 4 | H11: 3 | I11: =ROUND(F11*G11*H11/100,2) | J11: High | K11: Monitor, prepare internal memo and engage via association | L11: Risk
A13: Consolidation Note | B13: Risk_Radar and Regulatory_News_Feed consolidated here. Use Policy_Monitoring as the single source for policy signals, probability, impact and recommended actions.
A15: Consolidated Risk Radar Items
A16: Risk ID | B16: Regulatory Topic | C16: Agency | D16: Probability (1-5) | E16: Impact (1-5) | F16: Preparedness (1-5) | G16: Risk Score | H16: Risk Level | I16: Early Warning Signal | J16: Recommended Action | K16: Owner
A17: RR-001 | B17: Capital adequacy and solvency update | C17: ISA | D17: 4 | E17: 5 | F17: 3 | G17: =D4*E4/F4 | H17: High | I17: Draft circular discussion and industry consultation | J17: Prepare capital impact note and engage via IAV | K17: Finance + PA
A18: RR-002 | B18: Product approval process tightening | C18: ISA | D18: 5 | E18: 5 | F18: 3 | G18: =D5*E5/F5 | H18: High | I18: More detailed Q&A requests from regulator | J18: Create product dossier checklist and Q&A evidence bank | K18: Product + PA
A19: RR-003 | B19: Bancassurance conduct guideline | C19: SBV / MOF | D19: 4 | E19: 5 | F19: 3 | G19: =D6*E6/F6 | H19: High | I19: Banking sector conduct review and consumer complaints | J19: Develop customer-protection narrative and sales governance evidence | K19: Bancassurance + Compliance
A20: RR-004 | B20: Data localization and privacy enforcement | C20: MIC | D20: 4 | E20: 4 | F20: 2 | G20: =D7*E7/F7 | H20: High | I20: New data consultation and privacy inspections | J20: Prepare data-flow map and compliance briefing | K20: Digital + Legal
A21: RR-005 | B21: Consumer complaint transparency requirement | C21: VCA / ISA | D21: 3 | E21: 4 | F21: 3 | G21: =D8*E8/F8 | H21: Medium | I21: Increased complaint reporting and media attention | J21: Prepare complaint KPI pack and remediation narrative | K21: Compliance
A22: RR-006 | B22: Mandatory ESG disclosure | C22: MOF | D22: 3 | E22: 2 | F22: 3 | G22: =D9*E9/F9 | H22: Low | I22: Green finance roadmap and peer disclosure practices | J22: Create baseline ESG disclosure template | K22: Finance + PA
A24: Consolidated Regulatory News / Signal Items
A25: Signal ID | B25: Date | C25: Source / Agency | D25: Headline / Signal | E25: Category | F25: Auto Tag | G25: Relevance to Manulife | H25: Probability (1-5) | I25: Impact (1-5) | J25: Signal Score | K25: Suggested Action | L25: Owner | M25: Status
A26: NEWS-001 | B26: 46177 | C26: MOF | D26: Draft discussion on capital adequacy strengthening | E26: Capital | F26: Capital | G26: Potential increase in capital planning and reporting pressure | H26: 4 | I26: 5 | J26: =H5*I5 | K26: Prepare capital impact note and Finance briefing | L26: Finance / PA | M26: Monitoring
A27: NEWS-002 | B27: 46178 | C27: ISA | D27: Market conduct inspection activity increases across insurers | E27: Consumer Protection | F27: Market Conduct | G27: Higher scrutiny on complaints, sales conduct and product disclosure | H27: 5 | I27: 4 | J27: =H6*I6 | K27: Review complaint report and sales training evidence | L27: Compliance / PA | M27: Action Required
A28: NEWS-003 | B28: 46179 | C28: IAV | D28: Working group formed on standardized product disclosure | E28: Product Approval | F28: Product | G28: Opportunity to shape industry position on disclosure standards | H28: 3 | I28: 4 | J28: =H7*I7 | K28: Join working group and draft Manulife input | L28: Product / PA | M28: Open
A29: NEWS-004 | B29: 46180 | C29: MIC | D29: Consultation on data localization implementation guidance | E29: Data Privacy | F29: Data | G29: Potential impact on digital insurance and regional data processing | H29: 4 | I29: 4 | J29: =H8*I8 | K29: Prepare data-flow map and legal position | L29: IT / Legal | M29: Monitoring
A30: NEWS-005 | B30: 46181 | C30: SBV | D30: Review of bancassurance sales practice risk | E30: Distribution | F30: Bancassurance | G30: Potential change to bank channel monitoring requirements | H30: 4 | I30: 5 | J30: =H9*I9 | K30: Coordinate with bank partners and Compliance | L30: Distribution | M30: Action Required
A31: NEWS-006 | B31: 46183 | C31: Regional Office | D31: APAC request for ESG disclosure readiness update | E31: ESG | F31: ESG | G31: Need consistent local-to-regional ESG reporting pack | H31: 3 | I31: 3 | J31: =H10*I10 | K31: Prepare ESG readiness note | L31: Strategy / PA | M31: Open

Sheet Translation_Tracker
A1: Document ID | B1: Document Name | C1: Direction | D1: Owner | E1: Received Date | F1: Due Date | G1: Status | H1: SLA Days | I1: Notes
A2: TR-001 | B2: Circular summary 1 | C2: VN -> EN | D2: Legal | E2: 46182 | F2: 46183 | G2: Not Started | H2: =F2-E2 | I2: Sample
A3: TR-002 | B3: Official letter 2 | C3: VN -> EN | D3: Compliance | E3: 46173 | F3: 46180 | G3: Done | H3: =F3-E3 | I3: Sample
A4: TR-003 | B4: Meeting note 3 | C4: EN -> VN | D4: Compliance | E4: 46181 | F4: 46185 | G4: Not Started | H4: =F4-E4 | I4: Sample
A5: TR-004 | B5: Meeting note 4 | C5: EN -> VN | D5: Public Affairs | E5: 46175 | F5: 46180 | G5: In Progress | H5: =F5-E5 | I5: Sample
A6: TR-005 | B6: Regional report 5 | C6: VN -> EN | D6: Public Affairs | E6: 46180 | F6: 46186 | G6: Done | H6: =F6-E6 | I6: Sample
A7: TR-006 | B7: Circular summary 6 | C7: EN -> VN | D7: Compliance | E7: 46167 | F7: 46170 | G7: In Progress | H7: =F7-E7 | I7: Sample
A8: TR-007 | B8: Product dossier 7 | C8: VN -> EN | D8: Compliance | E8: 46171 | F8: 46178 | G8: Done | H8: =F8-E8 | I8: Sample
A9: TR-008 | B9: Meeting note 8 | C9: EN -> VN | D9: Legal | E9: 46184 | F9: 46186 | G9: Done | H9: =F9-E9 | I9: Sample
A10: TR-009 | B10: Official letter 9 | C10: EN -> VN | D10: Public Affairs | E10: 46184 | F10: 46186 | G10: In Progress | H10: =F10-E10 | I10: Sample
A11: TR-010 | B11: Circular summary 10 | C11: VN -> EN | D11: Legal | E11: 46164 | F11: 46165 | G11: Overdue | H11: =F11-E11 | I11: Sample
A12: TR-011 | B12: Official letter 11 | C12: EN -> VN | D12: Legal | E12: 46170 | F12: 46173 | G12: Done | H12: =F12-E12 | I12: Sample
A13: TR-012 | B13: Circular summary 12 | C13: VN -> EN | D13: Public Affairs | E13: 46166 | F13: 46171 | G13: In Progress | H13: =F13-E13 | I13: Sample
... A21: TR-020 | B21: Official letter 20 | C21: EN -> VN | D21: Public Affairs | E21: 46172 | F21: 46177 | G21: Overdue | H21: =F21-E21 | I21: Sample

Sheet Reference_Lists
A1: Status | B1: Priority | C1: Risk Level | D1: Document Type | E1: Direction | F1: Escalation Level
A2: On Track | B2: Critical | C2: Critical | D2: Report | E2: Incoming | F2: Level 0
A3: Due Soon | B3: High | C3: High | D3: Official Letter | E3: Outgoing | F3: Level 1
A4: Overdue | B4: Medium | C4: Medium | D4: Product Dossier | E4: Internal | F4: Level 2
A5: Submitted | B5: Low | C5: Low | D5: Approval Request | E5: RO Reporting | F5: Level 3
A6: Approved | D6: Meeting Brief
A7: In Review | D7: Translation
A8: Drafting | D8: Regulator Response
A9: Waiting Internal Input | D9: Regional Office Report
A10: Open | D10: Other
A11: Closed
A12: In Progress
A14: Priority
A15: Critical
A16: High
A17: Medium
A18: Low
A20: Regulators
A21: MOF
A22: ISA
A23: IAV
A24: SBV
... A39: Risk

Sheet Daily_Control_Tower
A1: Daily Work Control Tower - Manulife VN Regulatory & Public Affairs
A3: KPI | B3: Formula / Source | C3: Value | D3: Interpretation
A4: Reports due this week | B4: Regulatory calendar due within 7 days | C4: =COUNTIFS(Regulatory_Calendar!F:F,">="&TODAY(),Regulatory_Calendar!F:F,"<="&TODAY()+7) | D4: Short-term workload
A5: Overdue regulatory items | B5: Calendar + submissions overdue | C5: =COUNTIF(Regulatory_Calendar!H:H,"Overdue")+COUNTIF(Submission_Tracker!I:I,"Overdue") | D5: Immediate escalation
A6: Pending MOF / ISA submissions | B6: Not yet submitted to MOF or ISA | C6: =COUNTIFS(Submission_Tracker!C:C,"MOF",Submission_Tracker!I:I,"<>Submitted")+COUNTIFS(Submission_Tracker!C:C,"ISA",Submission_Tracker!I:I,"<>Submitted") | D6: Key regulator workload
A7: Open regulator follow-ups | B7: Regulator interaction status open | C7: =COUNTIF(Regulator_Interactions!K:K,"Open")+COUNTIF(Regulator_Interactions!K:K,"In Progress") | D7: Relationship management
A8: Upcoming regulator meetings | B8: Interactions / follow-ups in next 14 days | C8: =COUNTIFS(Regulator_Interactions!J:J,">="&TODAY(),Regulator_Interactions!J:J,"<="&TODAY()+14) | D8: Preparation needs
A9: Documents pending QC | B9: Document checklist not approved | C9: =COUNTIF(Document_QC_Checklist!L:L,"Not Ready")+COUNTIF(Document_QC_Checklist!L:L,"Needs Review") | D9: Pre-submission control
A11: Priority Action List | B11: Source | C11: Item | D11: Regulator | E11: Owner | F11: Due Date | G11: Days Left | H11: Status | I11: Risk | J11: Required Action | K11: Escalation | L11: Notes
A12: Calendar | B12: Calendar | C12: Monthly solvency monitoring report | D12: ISA | E12: Product | F12: 46185 | G12: 1 | H12: Due Soon | I12: High | J12: Confirm source data and QA before submission | K12: No | L12: Prepare CEO Office note if delayed
A13: Submission | B13: Submission | C13: New product approval dossier | D13: MOF | E13: Legal | F13: 46187 | G13: 3 | H13: In Review | I13: Medium | J13: Complete official letter checklist and attachments | K13: No | L13: Coordinate with Compliance
A14: Meeting | B14: Meeting | C14: ISA technical working session | D14: ISA | E14: Public Affairs | F14: 46189 | G14: 5 | H14: Planned | I14: High | J14: Generate briefing note and talking points | K14: No | L14: Use meeting brief generator
A15: Translation | B15: Translation | C15: Circular summary VN to EN | D15: Regional Office | E15: Public Affairs | F15: 46186 | G15: 2 | H15: In Progress | I15: Medium | J15: Finalize English version for regional pack | K15: No | L15: Prioritize before weekly report
A16: QC | B16: QC | C16: Official letter to MOF | D16: MOF | E16: Regulatory Affairs | F16: 46184 | G16: 0 | H16: Needs Review | I16: High | J16: Verify signature authority and legal review | K16: Yes | L16: Escalate before 3pm
A18: How to use this tab
A19: This tab is designed as the default daily operating screen for the role. It converts the JD into a control tower: deadlines, regulator submissions, internal follow-ups, meeting preparation and document quality control. Review it every morning; update item owners and status during the day; escalate red items before end of day.

Sheet Document_QC_Checklist
A1: Document Quality Checklist - Official Letters / Reports / Dossiers
A3: Document ID | B3: Document Name | C3: Regulator | D3: Document Type | E3: Owner | F3: Due Date | G3: Correct Template | H3: Reference No. | I3: Signature Authority | J3: Legal Review | K3: Compliance Review | L3: Readiness Status | N3: QC Summary | O3: Formula | P3: Value | Q3: Comment
A4: DOC-001 | B4: Official letter re product approval | C4: MOF | D4: Official Letter | E4: Public Affairs | F4: 46187 | G4: Yes | H4: Yes | I4: Yes | J4: Yes | K4: Yes | L4: Ready | N4: Ready documents | O4: =COUNTIF(L:L,"Ready") | Q4: Can be submitted after final management approval
A5: DOC-002 | B5: Monthly solvency monitoring report | C5: ISA | D5: Regulatory Report | E5: Product | F5: 46185 | G5: Yes | H5: Yes | I5: Yes | J5: In Progress | K5: Yes | L5: Needs Review | N5: Needs review | O5: =COUNTIF(L:L,"Needs Review") | Q5: Follow up with Legal/Compliance/Owner
A6: DOC-003 | B6: Agency training approval dossier | C6: ISA | D6: Approval Dossier | E6: Agency | F6: 46191 | G6: Yes | H6: No | I6: Yes | J6: No | K6: In Progress | L6: Not Ready | N6: Not ready | O6: =COUNTIF(L:L,"Not Ready") | Q6: Escalate if due within 7 days
A7: DOC-004 | B7: Data privacy compliance update | C7: MIC | D7: Regulatory Report | E7: Compliance | F7: 46198 | G7: Yes | H7: Yes | I7: Yes | J7: Yes | K7: In Progress | L7: Needs Review
A8: DOC-005 | B8: Regional Office weekly regulatory pack | C8: Regional Office | D8: Management Report | E8: Public Affairs | F8: 46186 | G8: Yes | H8: N/A | I8: N/A | J8: N/A | K8: Yes | L8: Ready
A9: DOC-006 | B9: Capital increase supporting paper | C9: MOF | D9: Approval Dossier | E9: Finance | F9: 46194 | G9: Yes | H9: Yes | I9: Pending | J9: In Progress | K9: No | L9: Not Ready

Sheet Interview_Demo_Mode
A1: Interview Demo Mode - How to Present This Tool to Manulife
A3: Section | B3: Suggested Talking Points
A4: 1. Problem this tool solves | B4: The role requires accurate regulatory reporting, deadline control, document quality, regulator coordination and Regional Office reporting. This tool turns those responsibilities into a daily operating system.
A5: 2. Workflow | B5: Daily Control Tower → Regulatory Calendar → Submission Tracker → Document QC Checklist → Regulator Interaction Log → Meeting Brief → Regional Report Pack.
A6: 3. Example case | B6: If MOF requests an updated product approval dossier, I can track the request, assign owners, verify legal/compliance review, generate a meeting brief and include the issue in the Regional Office weekly pack.
A7: 4. Why Excel first | B7: Excel is practical, easy to audit and easy to share with Legal, Compliance, Product and Finance teams.
A8: 5. Why Streamlit next | B8: Streamlit adds automation, dashboarding, filtering, meeting brief generation and a more professional management view.
A9: 6. Business value | B9: Fewer missed deadlines, faster preparation for regulator meetings, stronger document control and clearer visibility for management.
A10: 7. Interview closing message | B10: My aim is not to build a complex system, but to create operational discipline for Regulatory & Public Affairs work from day one.
A13: Demo Script - 90 Seconds
A14: In this role, I understand that the core work is not only public affairs strategy, but day-to-day regulatory operations: tracking deadlines, reviewing official letters, coordinating with Legal and Compliance, submitting dossiers to MOF/ISA and preparing Regional Office updates. I built this model to demonstrate how I would organize the work. The Daily Control Tower shows urgent items. The Regulatory Calendar and Submission Tracker control deadlines. The Document QC Checklist reduces errors before documents go to regulators. The Meeting Brief Generator helps prepare CEO/EMT meetings with regulators. Over time, the same structure can be upgraded from Excel into Streamlit for automation and reporting.
A24: Consolidation Note | B24: Interview_Story_Mode and Demo_Script_Mode consolidated into Interview_Demo_Mode. Use one interview narrative only.

Sheet Regulator_CRM
A1: Regulator CRM / Institutional Memory
A3: Regulator | B3: Mandate / Role | C3: Key Units / Contact Point | D3: Relationship Strength (1-5) | E3: Sentiment | F3: Open Issues | G3: Pending Requests | H3: Next Engagement | I3: Engagement Owner | J3: Institutional Memory Note | K3: Power (1-5) | L3: Interest (1-5) | M3: Engagement Priority | N3: Key Concerns | O3: Relationship Risk Score
A4: MOF | B4: Insurance policy, capital and sector oversight | C4: Insurance policy department / administrative office | D4: 4 | E4: Positive | F4: Capital adequacy update; product approval process | G4: Quarterly capital note and market stability briefing | H4: Strategic dialogue next quarter | I4: CEO + Head of Public Affairs | J4: Maintain evidence-based, constructive tone; align with financial stability priorities | K4: 5 | L4: 5 | M4: Critical | N4: Capital strength, market stability | O4: =ROUND((B2*C2)/D2,2)
A5: ISA | B5: Insurance supervision, product approval, market conduct | C5: Product approval unit / supervision team | D5: 3 | E5: Neutral | F5: Product Q&A; market conduct documentation | G5: Technical clarification on new health rider | H5: Monthly technical session | I5: Legal + Compliance + PA | J5: Operational regulator; documentation quality and timely response matter most | K5: 5 | L5: 5 | M5: Critical | N5: Market conduct, product transparency | O5: =ROUND((B3*C3)/D3,2)
A6: IAV | B6: Industry coordination and collective advocacy | C6: Association secretariat / working groups | D6: 5 | E6: Positive | F6: Industry position on product approval circular | G6: Input to association policy paper | H6: Join working group this month | I6: Public Affairs | J6: Use industry channel for non-sensitive sector-wide policy points | K6: 3 | L6: 4 | M6: High | N6: Industry alignment | O6: =ROUND((B4*C4)/D4,2)
A7: SBV | B7: Cross-sector financial risk and bancassurance conduct | C7: Financial stability / banking supervision interface | D7: 3 | E7: Neutral | F7: Bancassurance conduct and bank distribution risk | G7: Industry dialogue via association | H7: Quarterly dialogue | I7: Government Relations Director | J7: Engage on systemic risk and customer protection; avoid narrow company-only framing | K7: 4 | L7: 3 | M7: High | N7: Bancassurance, system risk | O7: =ROUND((B5*C5)/D5,2)
A8: MIC | B8: Data, digital distribution, cybersecurity and data localization | C8: Data policy / cybersecurity consultation channel | D8: 2 | E8: Cautious | F8: Data localization and consent requirements | G8: Digital insurance compliance note | H8: Policy roundtable in two months | I8: Digital Policy Lead | J8: Relationship requires more technical credibility and early transparency | K8: 3 | L8: 4 | M8: Medium | N8: Data privacy and localization | O8: =ROUND((B6*C6)/D6,2)
A9: VCA | B9: Consumer protection and complaints oversight | C9: Consumer protection unit | D9: 3 | E9: Cautious | F9: Complaint handling transparency; mis-selling concerns | G9: Consumer education and complaint KPI note | H9: Consumer protection briefing | I9: Compliance + PA | J9: Frame as customer protection and transparency agenda | K9: 4 | L9: 4 | M9: High | N9: Consumer complaints | O9: =ROUND((B7*C7)/D7,2)
A202: Consolidation Note | B202: Merged Relationship_Intelligence into Regulator_CRM. Relationship_Intelligence sheet removed.

Sheet Knowledge_Base
A1: Regulatory Knowledge Base AI-lite
A3: Topic / Regulation | B3: Agency | C3: Summary | D3: Key Obligations | E3: Impact on Manulife | F3: Affected Departments | G3: Required Actions | H3: Status | I3: Owner | J3: Review Frequency
A4: Insurance Law / Amended Insurance Law | B4: MOF / ISA | C4: Core legal framework for insurance business, licensing, solvency, distribution and product obligations. | D4: Maintain licensed activities, solvency discipline, product compliance and market conduct standards. | E4: High impact on products, capital, reporting and distribution. | F4: Legal; Compliance; Finance; Product; Agency | G4: Maintain obligations register; update internal policies; train business owners. | H4: Active | I4: Legal + PA | J4: Quarterly
A5: Circular on Product Approval Process | B5: ISA | C5: Expected guidance tightening product filing, Q&A, disclosure and customer suitability documentation. | D5: Provide complete product dossier, customer disclosure evidence and timely responses to regulator questions. | E5: High impact on product launch timeline and internal approval process. | F5: Product; Legal; Compliance; PA | G5: Create product approval checklist and regulator Q&A tracker. | H5: Monitoring | I5: Product + PA | J5: Monthly
A6: Bancassurance Conduct Guidance | B6: SBV / MOF | C6: Guidance likely focused on sales practices, transparency and customer consent in bank distribution. | D6: Improve sales governance, disclosure and complaint handling evidence. | E6: High impact on bancassurance revenue, conduct risk and reputation. | F6: Bancassurance; Compliance; Legal; PA | G6: Prepare industry input; strengthen sales conduct monitoring. | H6: Drafting | I6: Bancassurance + Compliance | J6: Monthly
A7: Personal Data Protection / Data Localization | B7: MIC | C7: Rules on consent, data processing, cross-border transfer and storage obligations. | D7: Maintain consent records, privacy notices and controls over data sharing. | E7: Medium-high impact on digital sales and customer data operations. | F7: IT; Digital; Legal; Compliance; PA | G7: Map data flows; prepare compliance note for regulator engagement. | H7: Implementation | I7: Digital + Legal | J7: Monthly
A8: Consumer Protection Requirements | B8: VCA / ISA | C8: Rules and expectations around complaint transparency, mis-selling prevention and fair customer treatment. | D8: Maintain complaint records, remediation evidence and transparent customer communication. | E8: High reputation impact and can trigger regulatory scrutiny. | F8: Compliance; Operations; Agency; PA | G8: Build customer complaint dashboard and regulator-ready remediation pack. | H8: Effective soon | I8: Compliance + PA | J8: Monthly
A9: ESG Disclosure for Insurers | B9: MOF | C9: Emerging expectation for sustainability disclosure, responsible investment and social contribution reporting. | D9: Collect ESG data and align disclosures with group and local expectations. | E9: Medium impact; opportunity to strengthen legitimacy. | F9: Finance; Investment; Sustainability; PA | G9: Prepare baseline ESG disclosure template. | H9: Early consultation | I9: Finance + PA | J9: Quarterly

Sheet Workflow_Engine
A1: Regulatory Workflow Engine
A3: Workflow ID | B3: Workflow Name | C3: Stage | D3: Owner | E3: SLA Days | F3: Status | G3: Bottleneck | H3: Next Action | I3: Regulator / Audience | J3: Control Point
A4: WF-001 | B4: MOF official letter submission | C4: Request received | D4: Public Affairs | E4: 1 | F4: Completed | G4: None | H4: Log request and confirm scope | I4: MOF | J4: Request scope confirmation
A5: WF-001 | B5: MOF official letter submission | C5: Data collection | D5: Business Owner | E5: 3 | F5: In Progress | G5: Delayed supporting data | H5: Escalate to Product by noon | I5: MOF | J5: Data completeness check
A6: WF-001 | B6: MOF official letter submission | C6: Legal review | D6: Legal | E6: 2 | F6: Pending | G6: Awaiting draft | H6: Send version-controlled draft | I6: MOF | J6: Legal sign-off
A7: WF-001 | B7: MOF official letter submission | C7: Compliance review | D7: Compliance | E7: 2 | F7: Pending | G7: Awaiting Legal comments | H7: Review once legal draft locked | I7: MOF | J7: Compliance sign-off
A8: WF-001 | B8: MOF official letter submission | C8: Management approval | D8: CEO Office | E8: 2 | F8: Not Started | G8: Signature authority not confirmed | H8: Confirm signer and delegation matrix | I8: MOF | J8: Signature authority check
A9: WF-001 | B9: MOF official letter submission | C9: Submission | D9: Public Affairs | E9: 1 | F9: Not Started | G9: Hard copy not prepared | H9: Prepare cover letter, attachments and submission receipt | I9: MOF | J9: Submission evidence archive
A10: WF-001 | B10: MOF official letter submission | C10: Response tracking | D10: Public Affairs | E10: 5 | F10: Not Started | G10: No response yet | H10: Track receipt and expected feedback date | I10: MOF | J10: Regulator response log
A11: WF-002 | B11: ISA product approval dossier | C11: Draft dossier | D11: Product | E11: 5 | F11: Completed | G11: None | H11: Send to Legal/Compliance | I11: ISA | J11: Product dossier checklist
A12: WF-002 | B12: ISA product approval dossier | C12: Regulator Q&A | D12: Product + PA | E12: 7 | F12: In Progress | G12: Technical answers incomplete | H12: Prepare Q&A table with evidence | I12: ISA | J12: Q&A response quality check
A13: WF-003 | B13: Regional Office regulatory update | C13: Collect weekly updates | D13: Public Affairs | E13: 2 | F13: In Progress | G13: Inputs from functions late | H13: Send Friday reminder | I13: Regional Office | J13: One source of truth tracker

Sheet Executive_Brief
A1: Executive Brief Generator Data
A3: Brief Date | B3: Audience | C3: Executive Summary | D3: Top Deadline | E3: Top Risk | F3: Key Regulator Interaction | G3: Documents Not Ready | H3: Next 7-Day Priorities | I3: Prepared By
A4: 2026-06-11 | B4: CEO / EMT | C4: Regulatory operations are manageable but three items require leadership visibility: one overdue ISA follow-up, product approval Q&A, and MOF official letter readiness. | D4: Monthly solvency report due tomorrow to ISA | E4: Circular on product approval process: high business impact and consultation window within 0-3 months | F4: ISA technical session planned; MOF official letter readiness check pending | G4: 3 documents not ready or needing review | H4: Close overdue ISA follow-up; finalize MOF letter; prepare ISA product Q&A; send weekly Regional Office pack | I4: Public Affairs
A5: 2026-06-12 | B5: Regional Office | C5: No material new law detected. Key focus remains product approval process, data privacy implementation and consumer protection reporting. | D5: Regional Office weekly regulatory pack due today | E5: Bancassurance conduct guideline remains medium-high strategic risk | F5: IAV working group scheduled; MIC data privacy consultation monitored | G5: 2 documents require review | H5: Issue weekly pack; update policy radar; close legal comments on product dossier | I5: Public Affairs
A202: Consolidation Note | B202: Regional_Report_Pack and Monthly_RO_Report_Generator consolidated here. Use Audience column for CEO / Regional Office / Management.
A203: Regional Office Monthly Template | B203: Regional Office | C203: Monthly Regulatory & Public Affairs Report Pack - Template Section | Auto Summary / Suggested Content | Source Tab | Owner 1. Key regulatory developments | Summarize top 3 policy items by risk score. | Policy_Monitoring | PA 2. Regulatory submissions | Highlight overdue, due soon and submitted items. | Submission_Tracker | PA 3. Pending approvals | List product/capital/license approvals by stage. | Approval_Pipeline | PA + Business 4. Regulator interactions | Summarize meetings/calls and follow-up actions. | Regulator_Interactions | PA 5. Emerging risks | Use early warning from policy risk and relationship risk. | Policy_Monitoring + Relationship_Intelligence | PA 6. Next 30-day priorities | Actions, owners and escalation needs. | All trackers | PA Head Draft Narrative This month, the Regulatory & Public Affairs team continued to monitor key regulatory developments affecting the life insurance sector, including product approval rules, consumer protection requirements, data privacy implementation and capital adequacy discussions. Key priorities for the next 30 days are to close overdue submissions, prepare technical inputs for ISA/MOF discussions, and coordinate with Legal, Compliance and business teams to ensure timely and high-quality responses.
A204: Monthly RO Draft Generator | B204: Regional Office | C204: One-Click Monthly Regional Office Report Generator (English Draft) Field | Value | Notes | Section | Draft Text Reporting Month | June 2026 | Change monthly | 1. Executive Summary | Overall regulatory workload remains manageable. Key focus areas are product approval follow-up, consumer protection monitoring, and timely completion of periodic reports. Reports Submitted On Time | 18 | Sample data | 2. Key Regulatory Developments | No major finalized regulation this month. The team continues to monitor draft guidance on bancassurance, data privacy and consumer protection. Overdue Reports | 1 | Sample data | 3. Pending Approvals | Two approval items remain pending with the regulator: one product filing and one agent training-related submission. Follow-up actions have been assigned. Pending Approvals | 2 | Sample data | 4. Regulator Engagements | The team maintained regular working contact with ISA and MOF through technical follow-ups, document submissions and preparation for upcoming meetings. Regulator Meetings | 4 | Sample data | 5. Emerging Risks | Emerging risks include potential tightening of product approval requirements, heightened market conduct supervision and evolving data localization expectations. High Risk Policy Issues | 3 | Sample data | 6. Next Month Priorities | Priorities for next month are: close pending approval actions, prepare for upcoming regulator meetings, complete documentation quality checks, and update policy risk assessment. Internal Overdue Follow-ups | 2 | Sample data | 7. Support Needed from Regional Office | No immediate escalation is required. Regional guidance may be useful if new APAC-level interpretation is issued on data privacy or market conduct. Generated Monthly Report Draft To: Regional Office Subject: Vietnam Regulatory & Public Affairs Monthly Update - June 2026 1. Executive Summary Overall regulatory workload remains manageable. The main focus areas are product approval follow-up, consumer protection monitoring, and timely completion of regulatory reporting obligations. 2. Key Metrics - Reports submitted on time: 18 - Overdue reports: 1 - Pending approvals: 2 - Regulator meetings/interactions: 4 - High-risk policy issues: 3 - Internal overdue follow-ups: 2 3. Key Regulatory Developments No major finalized regulation was identified this month. The team continues to monitor draft guidance relating to bancassurance, data privacy, consumer protection and market conduct supervision. 4. Pending Approvals and Submissions Two approval items remain pending with the regulator: one product filing and one agent training-related submission. Responsible owners have been assigned and follow-up actions are being tracked. 5. Regulator Engagements The team maintained regular working contact with ISA and MOF through technical follow-ups, document submissions and preparation for upcoming meetings. 6. Emerging Risks Emerging risks include potential tightening of product approval requirements, increased market conduct review and evolving data localization expectations. 7. Next Month Priorities Priorities for next month are to close pending approval actions, prepare for upcoming regulator meetings, complete documentation quality checks and update the policy risk assessment.

Sheet Approval_Analytics
A1: Approval Time Analytics
A3: Regulator | B3: Approval Type | C3: No. of Cases | D3: Avg Days to Approval | E3: Median Days | F3: Longest Open Case | G3: Expected Approval Time Next Case | H3: Bottleneck | I3: Recommended Improvement
A4: ISA | B4: Product approval | C4: 12 | D4: 42 | E4: 38 | F4: APR-011 | G4: 45 | H4: Regulator Q&A and missing technical evidence | I4: Create standardized Q&A evidence pack and pre-check with Compliance
A5: MOF | B5: Capital / license | C5: 8 | D5: 55 | E5: 52 | F5: APR-005 | G5: 58 | H5: Management approval and hard-copy documentation | I5: Prepare signature matrix and document QC before internal approval
A6: IAV | B6: Industry working group input | C6: 6 | D6: 21 | E6: 18 | F6: APR-014 | G6: 24 | H6: Coordination with member companies | I6: Submit early draft positions and align through working group
A7: MIC | B7: Digital / data consultation | C7: 5 | D7: 36 | E7: 34 | F7: APR-019 | G7: 40 | H7: Technical interpretation and data mapping | I7: Maintain data-flow annex and privacy impact summary
A8: SBV / MOF | B8: Bancassurance matters | C8: 7 | D8: 48 | E8: 46 | F8: APR-018 | G8: 50 | H8: Cross-agency alignment and conduct evidence | I8: Prepare customer-protection narrative and complaint KPIs

Sheet PA_Scorecard
A1: Public Affairs Scorecard
A3: KPI Area | B3: Metric | C3: Target | D3: Current | E3: Gap | F3: RAG Status | G3: Interpretation | H3: Owner
A4: Regulatory Reporting | B4: On-time submission rate | C4: 0.98 | D4: 0.92 | E4: 0.06 | F4: Amber | G4: Operational discipline is improving but not yet target level | H4: Public Affairs
A5: Document Control | B5: Documents ready before deadline | C5: 0.95 | D5: 0.78 | E5: 0.17 | F5: Red | G5: Document quality checklist should be enforced earlier | H5: Public Affairs + Legal
A6: Regulator Relationship | B6: Average relationship strength | C6: 4 | D6: 3.33 | E6: 0.67 | F6: Amber | G6: MOF/IAV strong; MIC and ISA require further technical engagement | H6: Head of PA
A7: Policy Intelligence | B7: High-risk policy items with action plan | C7: 1 | D7: 0.9 | E7: 0.1 | F7: Amber | G7: Most risks have actions, but owners should be confirmed | H7: Public Affairs
A8: Approval Management | B8: Approvals closed within target SLA | C8: 0.9 | D8: 0.72 | E8: 0.18 | F8: Red | G8: Internal review and Q&A response are main bottlenecks | H8: Product + Legal
A9: Regional Reporting | B9: Regional reports issued on schedule | C9: 1 | D9: 1 | E9: 0 | F9: Green | G9: Reporting discipline meets expectation | H9: Public Affairs
A10: Translation Support | B10: Translation tasks on-time | C10: 0.95 | D10: 0.85 | E10: 0.1 | F10: Amber | G10: Track SLA for Regional Office documents | H10: Public Affairs

Sheet Regulatory_Obligation_Register
A1: Regulatory Obligation Register
A2: Master inventory of recurring/ad-hoc regulatory obligations for Manulife Vietnam
A4: Obligation ID | B4: Obligation | C4: Regulator | D4: Legal Basis / Source | E4: Frequency | F4: Owner Dept | G4: Submission Channel | H4: Due Rule | I4: Next Due Date | J4: Penalty / Consequence | K4: Criticality | L4: Evidence Required | M4: Control Owner | N4: Status | O4: Days to Due | P4: RAG
A5: OBL-001 | B5: Monthly solvency monitoring report | C5: ISA / MOF | D5: Insurance Law / MOF guidance | E5: Monthly | F5: Finance | G5: e-Portal + hard copy | H5: 10th working day | I5: 46193 | J5: Regulatory reminder / inspection focus | K5: Critical | L5: Signed report, calculation file, management approval | M5: Regulatory Affairs | N5: Open | O5: =I5-TODAY() | P5: =IF(O5<0,"Red",IF(O5<=7,"Amber","Green"))
A6: OBL-002 | B6: Quarterly capital adequacy report | C6: MOF | D6: Insurance supervisory reporting rules | E6: Quarterly | F6: Finance / Risk | G6: Hard copy + official letter | H6: Quarter end + 15 days | I6: 46218 | J6: High regulatory concern if delayed | K6: Critical | L6: Actuary sign-off, Finance review, Compliance review | M6: Finance | N6: Open | O6: =I6-TODAY() | P6: =IF(O6<0,"Red",IF(O6<=7,"Amber","Green"))
A7: OBL-003 | B7: New product filing / approval dossier | C7: ISA | D7: Product approval requirements | E7: Ad-hoc | F7: Product / Legal | G7: Hard copy one-stop desk | H7: Before launch | I7: 46201 | J7: Product launch delay | K7: High | L7: Product wording, pricing note, disclosure, legal opinion | M7: Product | N7: In Progress | O7: =I7-TODAY() | P7: =IF(O7<0,"Red",IF(O7<=7,"Amber","Green"))
A8: OBL-004 | B8: Agent training program registration | C8: ISA | D8: Agency management regulation | E8: Ad-hoc | F8: Agency / Distribution | G8: Hard copy | H8: Before training roll-out | I8: 46191 | J8: Training delay / distribution impact | K8: Medium | L8: Training materials, trainer list, timetable | M8: Agency | N8: Open | O8: =I8-TODAY() | P8: =IF(O8<0,"Red",IF(O8<=7,"Amber","Green"))
A9: OBL-005 | B9: Anti-money laundering periodic update | C9: SBV / MOF | D9: AML regulatory framework | E9: Quarterly | F9: Compliance | G9: e-Portal | H9: Quarter end + 20 days | I9: 46223 | J9: Compliance finding | K9: High | L9: AML statistics, suspicious transaction controls | M9: Compliance | N9: Open | O9: =I9-TODAY() | P9: =IF(O9<0,"Red",IF(O9<=7,"Amber","Green"))
A10: OBL-006 | B10: Personal data processing compliance update | C10: MIC / MPS | D10: Personal data protection decree | E10: Annual / Ad-hoc | F10: IT / Legal | G10: Official letter | H10: Upon request / annual refresh | I10: 46239 | J10: Data privacy remediation order | K10: High | L10: DPIA, consent process, data inventory | M10: Legal | N10: Monitoring | O10: =I10-TODAY() | P10: =IF(O10<0,"Red",IF(O10<=7,"Amber","Green"))
A11: OBL-007 | B11: Consumer complaint handling report | C11: MOF / ISA | D11: Market conduct supervision | E11: Monthly | F11: Customer Service | G11: Email + hard copy | H11: 5th working day | I11: 46188 | J11: Market conduct scrutiny | K11: High | L11: Complaint log, resolution SLA, root-cause analysis | M11: Customer Service | N11: Open | O11: =I11-TODAY() | P11: =IF(O11<0,"Red",IF(O11<=7,"Amber","Green"))
A12: OBL-008 | B12: Bancassurance conduct update | C12: MOF / ISA / SBV | D12: Bancassurance supervision guidance | E12: Ad-hoc | F12: Partnership Distribution | G12: Working group / letter | H12: Upon regulator request | I12: 46205 | J12: Distribution channel restriction risk | K12: High | L12: Sales scripts, training evidence, bank partner data | M12: Distribution | N12: Open | O12: =I12-TODAY() | P12: =IF(O12<0,"Red",IF(O12<=7,"Amber","Green"))
A13: OBL-009 | B13: ESG / sustainable finance disclosure readiness | C13: MOF | D13: ESG disclosure roadmap | E13: Annual | F13: Strategy / Finance | G13: Regional pack + local submission | H13: Annual planning cycle | I13: 46295 | J13: Reputation / regional reporting gap | K13: Medium | L13: ESG KPI, governance note, investment policy summary | M13: Strategy | N13: Monitoring | O13: =I13-TODAY() | P13: =IF(O13<0,"Red",IF(O13<=7,"Amber","Green"))
A14: OBL-010 | B14: Regulator meeting minutes and action tracking | C14: MOF / ISA / IAV | D14: Internal PA operating standard | E14: After each meeting | F14: Regulatory & PA | G14: Internal archive | H14: 2 working days after meeting | I14: 46186 | J14: Loss of institutional memory | K14: Medium | L14: Minutes, action log, owner confirmation | M14: Regulatory Affairs | N14: Open | O14: =I14-TODAY() | P14: =IF(O14<0,"Red",IF(O14<=7,"Amber","Green"))

Sheet Regulatory_Response_Tracker
A1: Regulatory Response Tracker
A2: Track incoming/outgoing official letters, regulator requests and response SLA
A4: Ref No | B4: Date Received / Sent | C4: Direction | D4: Regulator | E4: Topic | F4: Linked Obligation / Submission | G4: Internal Owner | H4: Response Due Date | I4: Status | J4: Response Sent Date | K4: Days Open | L4: SLA Status | M4: Next Action | N4: Archive Location
A5: ISA-IN-2026-021 | B5: 46178 | C5: Incoming | D5: ISA | E5: Clarification on product filing dossier | F5: OBL-003 | G5: Product / Legal | H5: 46187 | I5: Open | K5: =IF(J5="",TODAY()-B5,J5-B5) | L5: =IF(AND(J5="",H5<TODAY()),"Overdue",IF(AND(J5="",H5-TODAY()<=3),"Due Soon","On Track")) | M5: Prepare Q&A and supporting product disclosure | N5: /Regulatory/ISA/ProductA/
A6: MOF-OUT-2026-034 | B6: 46179 | C6: Outgoing | D6: MOF | E6: Quarterly capital adequacy submission | F6: OBL-002 | G6: Finance | H6: 46218 | I6: Waiting Reply | J6: 46179 | K6: =IF(J6="",TODAY()-B6,J6-B6) | L6: =IF(AND(J6="",H6<TODAY()),"Overdue",IF(AND(J6="",H6-TODAY()<=3),"Due Soon","On Track")) | M6: Monitor acknowledgement from MOF | N6: /Regulatory/MOF/Capital/
A7: MOF-IN-2026-022 | B7: 46180 | C7: Incoming | D7: MOF | E7: Request for complaint-handling statistics | F7: OBL-007 | G7: Customer Service | H7: 46188 | I7: In Progress | K7: =IF(J7="",TODAY()-B7,J7-B7) | L7: =IF(AND(J7="",H7<TODAY()),"Overdue",IF(AND(J7="",H7-TODAY()<=3),"Due Soon","On Track")) | M7: Collect complaint SLA data and root-cause summary | N7: /Regulatory/MOF/MarketConduct/
A8: SBV-IN-2026-006 | B8: 46175 | C8: Incoming | D8: SBV | E8: Bancassurance conduct information request | F8: OBL-008 | G8: Distribution / Compliance | H8: 46185 | I8: Open | K8: =IF(J8="",TODAY()-B8,J8-B8) | L8: =IF(AND(J8="",H8<TODAY()),"Overdue",IF(AND(J8="",H8-TODAY()<=3),"Due Soon","On Track")) | M8: Align data with bank partner before response | N8: /Regulatory/SBV/Banca/
A9: MIC-IN-2026-004 | B9: 46170 | C9: Incoming | D9: MIC | E9: Data localization consultation draft | F9: OBL-006 | G9: IT / Legal | H9: 46193 | I9: In Progress | K9: =IF(J9="",TODAY()-B9,J9-B9) | L9: =IF(AND(J9="",H9<TODAY()),"Overdue",IF(AND(J9="",H9-TODAY()<=3),"Due Soon","On Track")) | M9: Submit industry feedback through IAV where appropriate | N9: /Regulatory/MIC/Data/
A10: IAV-IN-2026-011 | B10: 46176 | C10: Incoming | D10: IAV | E10: Industry working group on product transparency | F10: OBL-003 | G10: Regulatory & PA | H10: 46186 | I10: Closed | J10: 46183 | K10: =IF(J10="",TODAY()-B10,J10-B10) | L10: =IF(AND(J10="",H10<TODAY()),"Overdue",IF(AND(J10="",H10-TODAY()<=3),"Due Soon","On Track")) | M10: Prepare internal summary of IAV position | N10: /Regulatory/IAV/ProductTransparency/
A11: ISA-OUT-2026-035 | B11: 46182 | C11: Outgoing | D11: ISA | E11: Agent training materials registration | F11: OBL-004 | G11: Agency | H11: 46191 | I11: Submitted | J11: 46182 | K11: =IF(J11="",TODAY()-B11,J11-B11) | L11: =IF(AND(J11="",H11<TODAY()),"Overdue",IF(AND(J11="",H11-TODAY()<=3),"Due Soon","On Track")) | M11: Wait for receipt stamp and update archive | N11: /Regulatory/ISA/AgentTraining/

Sheet Product_Approval_Command_Center
A1: Product Approval Command Center
A2: Dedicated tracker for product approval dossiers, bottlenecks and expected timeline
A4: Product ID | B4: Product Name | C4: Product Type | D4: Business Owner | E4: Regulator | F4: Current Stage | G4: Request Date | H4: Submitted Date | I4: Target Approval Date | J4: Expected Approval Days | K4: Actual Approval Date | L4: Bottleneck | M4: Approval Risk | N4: Next Action
A5: PROD-001 | B5: FutureCare UL Plus | C5: Unit-linked | D5: Product | E5: ISA | F5: Regulator Review | G5: 46154 | H5: 46175 | I5: 46218 | J5: =IF(K5="",I5-G5,K5-G5) | L5: Additional disclosure questions | M5: Medium | N5: Prepare written clarification on benefit illustration
A6: PROD-002 | B6: Health Shield Rider 2026 | C6: Health rider | D6: Product / Actuary | E6: ISA | F6: Internal Legal Review | G6: 46174 | I6: 46233 | J6: =IF(K6="",I6-G6,K6-G6) | L6: Legal wording and exclusion clauses | M6: Medium | N6: Finalize wording and submit to Compliance
A7: PROD-003 | B7: Retirement Income Plan | C7: Pension / savings | D7: Product / Finance | E7: ISA | F7: Drafting | G7: 46178 | I7: 46254 | J7: =IF(K7="",I7-G7,K7-G7) | L7: Pricing assumptions alignment | M7: Low | N7: Complete actuarial memo
A8: PROD-004 | B8: Family Protection 2026 | C8: Traditional life | D8: Product | E8: ISA | F8: Approved | G8: 46127 | H8: 46147 | I8: 46198 | J8: =IF(K8="",I8-G8,K8-G8) | K8: 46181 | L8: None | M8: Low | N8: Archive approval and notify distribution
A9: PROD-005 | B9: Digital Term Life | C9: Protection / digital | D9: Digital / Product | E9: ISA / MIC | F9: Pre-consultation | G9: 46176 | I9: 46275 | J9: =IF(K9="",I9-G9,K9-G9) | L9: Data consent and e-KYC process | M9: High | N9: Hold pre-consultation with data/legal team
A10: PROD-006 | B10: Banca Savings Plan | C10: Bancassurance | D10: Partnership Distribution | E10: ISA / SBV | F10: On Hold | G10: 46162 | I10: 46239 | J10: =IF(K10="",I10-G10,K10-G10) | L10: Bancassurance conduct review | M10: High | N10: Await internal conduct remediation evidence

Sheet Internal_Coordination_Tracker
A1: Internal Coordination Tracker
A2: Follow-up matrix with Legal, Compliance, Product, Finance, Distribution and Regional Office
A4: Item ID | B4: Department | C4: Request / Input Needed | D4: Linked Matter | E4: Request Date | F4: Due Date | G4: SLA Days | H4: Owner | I4: Status | J4: Escalation | K4: Days to Due | L4: Reminder Sent | M4: Management Attention
A5: INT-001 | B5: Legal | C5: Review official letter to ISA for product clarification | D5: PROD-001 | E5: 46181 | F5: 46186 | G5: =F5-E5 | H5: Legal Counsel | I5: In Progress | J5: No | K5: =F5-TODAY() | L5: Yes | M5: =IF(K5<0,"Yes",IF(AND(K5<=2,I5<>"Done"),"Potential","No"))
A6: INT-002 | B6: Compliance | C6: Confirm market conduct controls for bancassurance response | D6: SBV-IN-2026-006 | E6: 46179 | F6: 46185 | G6: =F6-E6 | H6: Compliance Manager | I6: Pending | J6: Yes | K6: =F6-TODAY() | L6: Yes | M6: =IF(K6<0,"Yes",IF(AND(K6<=2,I6<>"Done"),"Potential","No"))
A7: INT-003 | B7: Finance | C7: Provide capital adequacy figures and management sign-off | D7: OBL-002 | E7: 46183 | F7: 46191 | G7: =F7-E7 | H7: Finance Controller | I7: Open | J7: No | K7: =F7-TODAY() | L7: No | M7: =IF(K7<0,"Yes",IF(AND(K7<=2,I7<>"Done"),"Potential","No"))
A8: INT-004 | B8: Product | C8: Update product disclosure comparison table | D8: PROD-001 | E8: 46182 | F8: 46187 | G8: =F8-E8 | H8: Product Lead | I8: In Progress | J8: No | K8: =F8-TODAY() | L8: Yes | M8: =IF(K8<0,"Yes",IF(AND(K8<=2,I8<>"Done"),"Potential","No"))
A9: INT-005 | B9: Customer Service | C9: Extract monthly complaint statistics and root-cause analysis | D9: MOF-IN-2026-022 | E9: 46180 | F9: 46186 | G9: =F9-E9 | H9: CS Manager | I9: In Progress | J9: No | K9: =F9-TODAY() | L9: Yes | M9: =IF(K9<0,"Yes",IF(AND(K9<=2,I9<>"Done"),"Potential","No"))
A10: INT-006 | B10: IT / Data | C10: Validate data processing inventory for MIC consultation | D10: MIC-IN-2026-004 | E10: 46178 | F10: 46192 | G10: =F10-E10 | H10: Data Privacy Officer | I10: Open | J10: No | K10: =F10-TODAY() | L10: No | M10: =IF(K10<0,"Yes",IF(AND(K10<=2,I10<>"Done"),"Potential","No"))
A11: INT-007 | B11: Regional Office | C11: Confirm APAC position on ESG disclosure readiness | D11: OBL-009 | E11: 46183 | F11: 46198 | G11: =F11-E11 | H11: Regional PA | I11: Open | J11: No | K11: =F11-TODAY() | L11: No | M11: =IF(K11<0,"Yes",IF(AND(K11<=2,I11<>"Done"),"Potential","No"))

Sheet Meeting_Intelligence
A1: Meeting Intelligence
A2: Before-meeting preparation and after-meeting commitments/action tracking
A4: Meeting ID | B4: Date | C4: Regulator | D4: Topic | E4: Meeting Type | F4: Pre-Meeting Objective | G4: Key Talking Points | H4: Potential Regulator Questions | I4: Recommended Position | J4: Commitments Made | K4: Action Owner | L4: Action Due Date | M4: Status | N4: Institutional Memory Note | O4: Linked Documents
A5: MTG-001 | B5: 46187 | C5: ISA | D5: Product approval clarification | E5: Technical session | F5: Clarify disclosure and benefit illustration questions | G5: Customer protection; transparent illustration; internal controls | H5: How does the product avoid mis-selling? What disclosures are provided? | I5: Support ISA's customer protection objective with evidence | J5: Submit revised Q&A and disclosure note | K5: Product / Legal | L5: 46190 | M5: Open | N5: ISA focused strongly on customer understanding and sales training evidence | O5: PROD-001 dossier
A6: MTG-002 | B6: 46191 | C6: MOF | D6: Capital adequacy reporting | E6: Strategic dialogue | F6: Confirm reporting expectations and timeline | G6: Capital strength; consistency; no delay | H6: Are solvency assumptions consistent with last quarter? | I6: Transparent and technical, avoid over-promising | J6: Provide signed actuarial memo | K6: Finance | L6: 46195 | M6: Open | N6: MOF values concise explanations and audited evidence | O6: Capital report pack
A7: MTG-003 | B7: 46193 | C7: IAV | D7: Product transparency working group | E7: Industry working group | F7: Align industry feedback on product disclosure | G7: Comparable disclosure; consumer education; implementation timeline | H7: Can industry agree on minimum disclosure standards? | I7: Use IAV channel to support balanced implementation | J7: Share Manulife draft position | K7: Regulatory & PA | L7: 46197 | M7: Open | N7: IAV can help aggregate technical input | O7: IAV memo
A8: MTG-004 | B8: 46198 | C8: MIC | D8: Data localization consultation | E8: Consultation meeting | F8: Understand data storage interpretation | G8: Data security; cross-border processing; customer consent | H8: What data is stored overseas and why? | I8: Acknowledge policy objective; propose practical transition period | J8: Submit data flow summary | K8: IT / Legal | L8: 46203 | M8: Planned | N8: MIC likely expects clear mapping of customer data flows | O8: Data privacy inventory
A10: Consolidation Note | B10: Merged Meeting_Brief into Meeting_Intelligence. Use this sheet for before-meeting briefs, commitments and follow-ups.
A11: Legacy Meeting Brief Summary | B11: Brief Field: Content | Meeting Title: ISA Technical Working Session - Product Approval | Date: 2026-06-11 00:00:00 | Purpose: Clarify regulator questions and present Manulife's compliance approach. | Background: Manulife has submitted a new product approval dossier and is awaiting technical feedback. | Key Talking Points: 1) Customer protection; 2) Product transparency; 3) Agent training; 4) Timely response to questions. | Potential Questions: How does Manulife prevent mis-selling? What disclosures are provided to customers? | Recommended Position: Support policy objectives, provide transparent evidence, avoid confrontational language. | Next Actions: Send follow-up note within 2 working days; assign owners for additional documents.

Sheet Inspection_Readiness
A1: Regulatory Inspection Readiness
A2: Self-assessment dashboard for regulator inspection preparedness
A4: Area | B4: Regulator Focus | C4: Required Evidence | D4: Owner | E4: Last Review Date | F4: Readiness Score (0-100) | G4: Gap | H4: Remediation Action | I4: Due Date | J4: Status | K4: RAG
A5: Regulatory reporting | B5: Timeliness and accuracy of periodic reports | C5: Submission log, signed reports, proof of receipt | D5: Regulatory Affairs | E5: 46174 | F5: 88 | G5: Some hard-copy receipts not archived | H5: Scan and archive receipt stamps | I5: 46193 | J5: In Progress | K5: =IF(F5<70,"Red",IF(F5<85,"Amber","Green"))
A6: Product filing | B6: Approval dossier completeness | C6: Product wordings, approval letters, actuarial memo | D6: Product / Legal | E6: 46176 | F6: 82 | G6: Benefit illustration Q&A pending | H6: Finalize regulator Q&A pack | I6: 46190 | J6: In Progress | K6: =IF(F6<70,"Red",IF(F6<85,"Amber","Green"))
A7: Market conduct | B7: Complaint handling and sales conduct | C7: Complaint log, training evidence, root cause analysis | D7: Compliance / CS | E7: 46178 | F7: 76 | G7: Root-cause analysis incomplete | H7: Complete complaint trend report | I7: 46188 | J7: Open | K7: =IF(F7<70,"Red",IF(F7<85,"Amber","Green"))
A8: Bancassurance | B8: Bank partner sales practice controls | C8: Partner training, scripts, monitoring evidence | D8: Distribution / Compliance | E8: 46170 | F8: 68 | G8: Bank partner data validation not complete | H8: Escalate to partnership distribution | I8: 46185 | J8: Escalated | K8: =IF(F8<70,"Red",IF(F8<85,"Amber","Green"))
A9: Data privacy | B9: Consent, data flow, localization readiness | C9: DPIA, consent logs, data map | D9: IT / Legal | E9: 46175 | F9: 74 | G9: Data flow inventory needs update | H9: Update customer data map | I9: 46203 | J9: Open | K9: =IF(F9<70,"Red",IF(F9<85,"Amber","Green"))
A10: Governance archive | B10: Institutional memory and document traceability | C10: Meeting minutes, official letters, tracker references | D10: Regulatory Affairs | E10: 46179 | F10: 90 | G10: No major gap | H10: Maintain monthly archive review | I10: 46208 | J10: On Track | K10: =IF(F10<70,"Red",IF(F10<85,"Amber","Green"))

Sheet Executive_Attention_Today
A1: What Requires Management Attention Today?
A2: One-page attention list for CEO/EMT and Regulatory & Public Affairs manager
A4: Priority | B4: Item | C4: Source Module | D4: Owner | E4: Due Date | F4: Why It Matters | G4: Recommended Decision / Action | H4: Status
A5: 1 | B5: Bancassurance conduct response due soon | C5: Regulatory Response Tracker | D5: Distribution / Compliance | E5: 46185 | F5: High regulator sensitivity and channel impact | G5: Escalate partner data validation and align final response | H5: Open
A6: 2 | B6: ISA product approval clarification | C6: Product Approval Command Center | D6: Product / Legal | E6: 46190 | F6: Directly affects product launch timeline | G6: Approve Q&A position and revised disclosure pack | H6: Open
A7: 3 | B7: Complaint handling data request from MOF | C7: Response Tracker / Internal Coordination | D7: Customer Service | E7: 46188 | F7: Market conduct risk and reputation exposure | G7: Finalize complaint statistics and root-cause summary | H7: In Progress
A8: 4 | B8: Data localization consultation | C8: Regulatory News Feed | D8: IT / Legal | E8: 46203 | F8: Potential digital/data processing business impact | G8: Prepare data-flow inventory and industry response | H8: Monitoring
A9: 5 | B9: Inspection readiness gap in bancassurance | C9: Inspection Readiness | D9: Compliance / Distribution | E9: 46185 | F9: Readiness score below target threshold | G9: Complete evidence pack or escalate remediation | H9: Escalated

Sheet Data_Dictionary_User_Guide
A1: Data Dictionary & User Guide - Handover-Ready Operating Manual
A3: Sheet / Module | B3: Purpose | C3: Primary User | D3: Update Frequency | E3: Key Inputs | F3: Key Outputs | G3: Typical KPI | H3: Notes
A4: Executive_Dashboard | B4: Senior summary of overall PA/regulatory workload and risk. | C4: Head of Regulatory & Public Affairs | D4: Weekly | E4: All tracker data | F4: KPIs, alerts, priorities | G4: Overall PA effectiveness | H4: Use in weekly management update.
A5: Daily_Control_Tower | B5: Daily view of urgent work items. | C5: PA Executive | D5: Daily | E5: Deadlines, actions, meetings | F5: Today/this-week priorities | G5: Overdue actions | H5: Open first every morning.
A6: Regulatory_Obligation_Register | B6: Master register of recurring and ad-hoc regulatory obligations. | C6: PA + Compliance | D6: Monthly or when rules change | E6: Obligation, regulator, owner, frequency, penalty | F6: Obligation map | G6: On-time completion rate | H6: Core control document.
A7: Regulatory_Calendar | B7: Calendar of report due dates and regulatory milestones. | C7: PA Executive | D7: Daily/weekly | E7: Due date, regulator, owner, status | F7: Deadline countdown | G7: Reports due in 7 days | H7: Feeds daily attention view.
A8: Submission_Tracker | B8: Tracks outgoing regulatory submissions. | C8: PA Executive | D8: Daily | E8: Submission details, status, ref no. | F8: Submission status | G8: On-time submission rate | H8: Use for MOF/ISA filings.
A9: Regulatory_Response_Tracker | B9: Tracks incoming/outgoing regulatory letters and pending responses. | C9: PA + Legal | D9: Daily | E9: Request, response owner, due date | F9: Open regulator requests | G9: Average response time | H9: Useful for audit trail.
A10: Product_Approval_Command_Center | B10: Tracks product/license/capital approval workflow. | C10: Product + PA + Legal | D10: Weekly | E10: Product, regulator, stage, owner | F10: Approval pipeline | G10: Average approval days | H10: Important for business enablement.
A11: Internal_Coordination_Tracker | B11: Tracks follow-up with internal departments. | C11: PA Executive | D11: Daily | E11: Department, action, SLA, owner | F11: Overdue internal actions | G11: SLA compliance | H11: Supports cross-functional discipline.
A12: Regulator_CRM | B12: Regulator relationship database. | C12: PA team | D12: After each meeting/contact | E12: Profile, contact history, open issues | F12: Relationship map | G12: Relationship score | H12: Institutional memory.
A13: Meeting_Intelligence | B13: Before/after meeting brief and action log. | C13: PA + EMT | D13: Per meeting | E13: Objective, talking points, commitments | F13: Meeting brief and follow-ups | G13: Follow-up closure rate | H13: Fits JD briefing notes.
A14: Document_QC_Checklist | B14: Quality control for official letters/reports before submission. | C14: PA + Legal + Compliance | D14: Per submission | E14: Template, attachment, review status | F14: Ready/not ready decision | G14: QC pass rate | H14: Pre-submission control gate.
... A22: Monthly_RO_Report_Generator | B22: One-click style monthly report text for Regional Office. | C22: PA team | D22: Monthly | E22: Trackers + narrative fields | F22: English report | G22: Report production time | H22: New in v6 polish.

Sheet SLA_Escalation_Rules
A1: SLA & Escalation Rules
A2: Operational rules for deadlines, regulator requests, internal follow-ups and document quality control.
A4: Process / Item Type | B4: Default SLA | C4: Trigger Condition | D4: Escalation Level | E4: Escalation Owner | F4: Recommended Action | G4: Email Template | H4: RAG Logic
A5: Periodic regulatory report | B5: Due date - 7 days | C5: Less than 7 calendar days to due date | D5: Level 1 | E5: Public Affairs owner | F5: Send reminder to internal owner | G5: Internal Reminder | H5: Amber
A6: Periodic regulatory report | B6: Due date passed | C6: Due date < today and not submitted | D6: Level 2 | E6: Head of Regulatory & Public Affairs | F6: Escalate to department head and agree recovery date | G6: Escalation Notice | H6: Red
A7: Ad-hoc regulator request | B7: Same day acknowledgement | C7: Request from MOF/ISA marked urgent or critical | D7: Level 2 | E7: Head of Regulatory & Public Affairs | F7: Confirm scope, owner and expected submission timeline | G7: Regulator Acknowledgement | H7: Red
A8: Legal / Compliance review | B8: 3 working days | C8: Review pending more than 3 days | D8: Level 1 | E8: Legal / Compliance focal point | F8: Send follow-up and propose deadline | G8: Internal Reminder | H8: Amber
A9: Management approval | B9: 2 working days | C9: CEO/EMT approval pending more than 2 days | D9: Level 2 | E9: CEO Office / EMT secretary | F9: Escalate through management office | G9: Escalation Notice | H9: Amber
A10: Product approval dossier | B10: 10 days before target date | C10: No regulator feedback or open clarification | D10: Level 1 | E10: Product + Public Affairs | F10: Prepare follow-up note to ISA/MOF | G10: Regulator Follow-up | H10: Amber
A11: Document QC | B11: Before submission | C11: Any mandatory checklist item = No | D11: Level 1 | E11: Document owner | F11: Hold submission until QC cleared | G11: Internal Reminder | H11: Red
A12: Translation request | B12: SLA passed | C12: Translation not completed by due date | D12: Level 1 | E12: Translation owner | F12: Follow up and update expected completion date | G12: Internal Reminder | H12: Amber
A13: Regional Office monthly report | B13: Monthly closing + 3 days | C13: RO pack not finalized | D13: Level 1 | E13: Public Affairs owner | F13: Compile metrics, risks and next-month priorities | G13: RO Monthly Update | H13: Amber

Sheet Email_Template_Generator
A1: Email Template Generator
A2: Ready-to-use English email templates for regulatory follow-up, internal reminders and Regional Office updates.
A4: Template ID | B4: Use Case | C4: Subject | D4: Recipient Type | E4: Trigger | F4: Email Body Template
A5: EMAIL-001 | B5: Internal deadline reminder | C5: Reminder: Regulatory input required for [Item] by [Due Date] | D5: Internal department | E5: Due in 7 days | F5: Dear [Name], This is a kind reminder that input for [Item] is required by [Due Date] for submission to [Regulator]. Please share the latest version and supporting documents by [Internal Deadline] so that Regulatory & Public Affairs can complete review and submission on time. Best regards, [Your Name]
A6: EMAIL-002 | B6: Internal escalation | C6: Escalation: Overdue regulatory input for [Item] | D6: Department head | E6: Overdue internal input | F6: Dear [Name], The input for [Item] is now overdue and may affect the regulatory submission timeline to [Regulator]. Please help prioritize this item and confirm the expected completion time. Best regards, [Your Name]
A7: EMAIL-003 | B7: Regulator acknowledgement | C7: Acknowledgement of request regarding [Topic] | D7: Regulator | E7: Incoming urgent request | F7: Dear [Title/Name], We acknowledge receipt of your request regarding [Topic]. We are coordinating with the relevant internal teams and will revert with the requested information by [Expected Date]. Respectfully, [Your Name]
A8: EMAIL-004 | B8: Regulator follow-up | C8: Follow-up on submitted dossier: [Dossier Name] | D8: Regulator | E8: No response after expected follow-up date | F8: Dear [Title/Name], We would like to respectfully follow up on the submitted dossier [Dossier Name], sent on [Submission Date]. Please let us know if any further clarification or supporting documents are required from our side. Respectfully, [Your Name]
A9: EMAIL-005 | B9: Meeting confirmation | C9: Meeting confirmation: [Regulator] / Manulife on [Date] | D9: Regulator / internal | E9: Meeting scheduled | F9: Dear [Name], Thank you for confirming the meeting on [Date] regarding [Topic]. We will prepare the relevant materials and proposed discussion points in advance. Best regards, [Your Name]
A10: EMAIL-006 | B10: Regional Office monthly update | C10: Vietnam Regulatory & Public Affairs Monthly Update - [Month] | D10: Regional Office | E10: Monthly reporting cycle | F10: Dear Regional Team, Please find below the Vietnam Regulatory & Public Affairs monthly update for [Month], covering key regulatory developments, pending approvals, regulator engagements, emerging risks and next-month priorities. Best regards, [Your Name]
